src/include/define.vh
`ifndef DEFINES_VH
`define DEFINES_VH

`define OP_IMM    7'b0010011
`define OP_LOAD   7'b0000011
`define OP_STORE  7'b0100011
`define OP_R_TYPE 7'b0110011

`endif

src/DMem.v
module DMem(
    input clk,
    input wire [31:0] addr,
    input wire [31:0] write_data,
    input wire mem_read,
    input wire mem_write,
    output wire [31:0] read_data
);

   
    reg [31:0] memory [0:4095];

    initial begin 
        for (integer i = 0; i < 4096; i = i + 1) begin
            memory[i] = 32'b0;
        end
    end
    
    always @(posedge clk) begin
        if (mem_write) begin
            memory[addr[13:2]] <= write_data;
        end
    end

    assign read_data = (mem_read) ? memory[addr[13:2]] : 32'b0;
endmodule

src/ALU.v
module ALU(
    input wire clk,
    input wire [31:0] operand1,
    input wire [31:0] operand2,
    input wire [3:0] alu_control,
    output reg [31:0] alu_result
);
    always @(*) begin
        case (alu_control)

            4'b0000: alu_result <= operand1 & operand2; 
            4'b0001: alu_result <= operand1 | operand2;
            4'b0010: alu_result <= operand1 + operand2;
            4'b0110: alu_result <= operand1 - operand2;
            4'b0111: alu_result <= (operand1 < operand2);
            4'b1100: alu_result <= ~(operand1 | operand2);
        endcase
    end
endmodule

src/ALUControl.v
module ALUControl(
    input wire clk,
    input wire [6:0] opcode,
    input wire [6:0] funct7,
    input wire [2:0] funct3,
    output reg [3:0] alu_control
);

    always @(*) begin
        if (opcode == `OP_LOAD || opcode == `OP_STORE) begin
            alu_control = 4'b0010; // Load/Store: ADD
        end else if (opcode == `OP_IMM) begin
            case (funct3)
                3'b000: alu_control = 4'b0010; // ADDI
                3'b111: alu_control = 4'b0000; // ANDI
                3'b110: alu_control = 4'b0001; // ORI
                3'b010: alu_control = 4'b0111; // SLTI
            endcase
        end else if (opcode == `OP_R_TYPE) begin
            case (funct3)
                3'b000: begin
                    if (funct7 == 7'b0100000) begin
                        alu_control = 4'b0110; // SUB
                    end else begin
                        alu_control = 4'b0010; // ADD
                    end
                end
                3'b111: alu_control = 4'b0000; // AND
                3'b110: alu_control = 4'b0001; // OR
                3'b010: alu_control = 4'b0111; // SLT
            endcase
        end else begin
            alu_control = 4'b1111; // NOP or undefined
            
        end
    end

endmodule

src/RegisterFile.v
module RegisterFile(
    input wire clk,
    input wire [4:0] read_reg1,
    input wire [4:0] read_reg2,
    input wire [4:0] write_reg,
    input wire [31:0] write_data,
    input wire reg_write,   
    output wire [31:0] read_data1,
    output wire [31:0] read_data2
);

    reg [31:0] register[0:31];

    integer i;
    initial begin
        for (i = 0; i < 32; i = i + 1) register[i] = 0;
    end

    always @(posedge clk) begin
    if (reg_write && (write_reg != 5'd0)) begin
        register[write_reg] <= write_data;
    end
    end

    assign read_data1 = (reg_write && (write_reg != 5'd0) && (write_reg == read_reg1)) ? write_data : register[read_reg1];
    assign read_data2 = (reg_write && (write_reg != 5'd0) && (write_reg == read_reg2)) ? write_data : register[read_reg2];

endmodule

src/Decoder.v
module Decoder(
    input wire clk,
    input wire [31:0] instruction,
    output reg [11:0] imm,
    output wire [6:0] funct7,
    output wire [4:0] rs2,
    output wire [4:0] rs1,
    output wire [2:0] funct3,
    output wire [4:0] rd,
    output wire [6:0] opcode
);
    `include "src/include/define.vh"
    
    assign funct7 = instruction[31:25];
    assign rs2 = instruction[24:20];
    assign rs1 = instruction[19:15];
    assign funct3 = instruction[14:12];
    assign rd = instruction[11:7];
    assign opcode = instruction[6:0];
    
    always @(*) begin
        if (opcode == `OP_STORE) begin
            imm = {instruction[31:25], instruction[11:7]};
        end else begin
            imm = instruction[31:20];
        end
    end    
endmodule

src/IMem.v
module IMem(
    input clk,
    input wire [31:0] addr,
    output wire [31:0] instruction
);
    reg [31:0] memory [0:255];
    assign instruction = memory[addr[9:2]];
    

    initial begin
        $readmemh("program/hex/r_type.hex", memory);
    end
    
    
endmodule

src/PC.v
module PC(
    input clk,
    input reset,
    input wire [31:0] pc_in,
    output reg [31:0] pc_out
);
    always @(posedge clk or posedge reset) begin
        if (reset) begin
            pc_out <= 32'b0;
        end else begin
            pc_out <= pc_in;
        end
    end
    
endmodule

src/CPU.v
module CPU(
    input wire clk,
    input wire reset
);

    `include "src/include/define.vh"

    wire [31:0] pc_out;

    PC PC(
        .clk(clk), 
        .reset(reset),
        .pc_in(pc_out + 4),
        .pc_out(pc_out)
    );  

    wire [31:0] instruction;

    IMem IMem(
        .clk(clk),
        .addr(pc_out),
        .instruction(instruction)
    );

    wire [6:0] opcode;
    wire [4:0] rs1;
    wire [4:0] rs2;
    wire [4:0] rd;
    wire [2:0] funct3;
    wire [6:0] funct7;
    wire [11:0] imm;

    Decoder Decoder(
        .clk(clk),
        .instruction(instruction),
        .imm(imm),
        .funct7(funct7),
        .rs2(rs2),
        .rs1(rs1),
        .funct3(funct3),
        .rd(rd),
        .opcode(opcode)
    );

    wire [31:0] reg_read_data1;
    wire [31:0] reg_read_data2;
    reg [31:0] reg_write_data;
    wire reg_write = 1'b1; 
    RegisterFile RegisterFile(
        .clk(clk),
        .read_reg1(rs1),
        .read_reg2(rs2),
        .write_reg(rd),
        .write_data(reg_write_data),
        .reg_write(reg_write),
        .read_data1(reg_read_data1),
        .read_data2(reg_read_data2)
    );

    wire [3:0] alu_control;
    
    ALUControl ALUControl(
        .clk(clk),
        .opcode(opcode),
        .funct7(funct7),
        .funct3(funct3),
        .alu_control(alu_control)
    );


    reg [31:0] alu_input1;
    reg [31:0] alu_input2;
    wire [31:0] alu_result;

    always @(*) begin
        case (opcode) 
            `OP_IMM: begin
                alu_input1 = reg_read_data1;
                alu_input2 = {{20{imm[11]}}, imm};
            end
            `OP_LOAD: begin
                alu_input1 = reg_read_data1;
                alu_input2 = {{20{imm[11]}}, imm};
            end
            `OP_STORE: begin
                alu_input1 = reg_read_data1;
                alu_input2 = {{20{imm[11]}}, imm};
            end
            `OP_R_TYPE: begin
                alu_input1 = reg_read_data1;
                alu_input2 = reg_read_data2;
            end
            default: begin
                alu_input1 = reg_read_data1;
                alu_input2 = 32'd0;
            end
        endcase
    end

    ALU ALU(
        .clk(clk),
        .operand1(alu_input1),
        .operand2(alu_input2),
        .alu_control(alu_control),
        .alu_result(alu_result)
    );


    wire [31:0] mem_read_data;
    DMem DMem(
        .clk(clk),
        .addr(alu_result),
        .write_data(reg_read_data2),
        .mem_read(opcode == `OP_LOAD),
        .mem_write(opcode == `OP_STORE),
        .read_data(mem_read_data)
    );


    reg MemtoReg;
    always @(*) begin
        case (opcode)
            `OP_LOAD:    MemtoReg = 1'b1;
            `OP_IMM:  MemtoReg = 1'b0;
            `OP_STORE:      MemtoReg = 1'b0;
            default:     MemtoReg = 1'b0;
        endcase
    end

    always @(*) begin
        reg_write_data = MemtoReg ? mem_read_data : alu_result;
    end

endmodule

tb/CPU_testbench.v
module CPU_testbench;
    reg clk = 0;
    reg reset = 0;

    always #1 begin 
        clk = ~clk;
    end

    initial begin
        $dumpfile("CPU_testbench.vcd");
        $dumpvars(0, CPU_testbench);
    end
    
    CPU CPU(
        .clk(clk),
        .reset(reset)
    );

    initial begin
        reset = 0;
        #4
        reset = 1;
        #3000
        $finish;
    end

endmodule

CPU_testbench.vcd
$date
	Tue Jan 13 16:03:22 2026
$end
$version
	Icarus Verilog
$end
$timescale
	1s
$end
$scope module CPU_testbench $end
$var reg 1 ! clk $end
$var reg 1 " reset $end
$scope module CPU $end
$var wire 1 ! clk $end
$var wire 1 # reg_write $end
$var wire 1 " reset $end
$var wire 5 $ rs2 [4:0] $end
$var wire 5 % rs1 [4:0] $end
$var wire 32 & reg_read_data2 [31:0] $end
$var wire 32 ' reg_read_data1 [31:0] $end
$var wire 5 ( rd [4:0] $end
$var wire 32 ) pc_out [31:0] $end
$var wire 7 * opcode [6:0] $end
$var wire 32 + mem_read_data [31:0] $end
$var wire 32 , instruction [31:0] $end
$var wire 12 - imm [11:0] $end
$var wire 7 . funct7 [6:0] $end
$var wire 3 / funct3 [2:0] $end
$var wire 32 0 alu_result [31:0] $end
$var wire 4 1 alu_control [3:0] $end
$var reg 1 2 MemtoReg $end
$var reg 32 3 alu_input1 [31:0] $end
$var reg 32 4 alu_input2 [31:0] $end
$var reg 32 5 reg_write_data [31:0] $end
$scope module ALU $end
$var wire 1 ! clk $end
$var wire 32 6 operand1 [31:0] $end
$var wire 32 7 operand2 [31:0] $end
$var wire 4 8 alu_control [3:0] $end
$var reg 32 9 alu_result [31:0] $end
$upscope $end
$scope module ALUControl $end
$var wire 1 ! clk $end
$var wire 7 : opcode [6:0] $end
$var wire 7 ; funct7 [6:0] $end
$var wire 3 < funct3 [2:0] $end
$var reg 4 = alu_control [3:0] $end
$upscope $end
$scope module DMem $end
$var wire 32 > addr [31:0] $end
$var wire 1 ! clk $end
$var wire 1 ? mem_read $end
$var wire 1 @ mem_write $end
$var wire 32 A read_data [31:0] $end
$var wire 32 B write_data [31:0] $end
$scope begin $ivl_for_loop0 $end
$var integer 32 C i [31:0] $end
$upscope $end
$upscope $end
$scope module Decoder $end
$var wire 1 ! clk $end
$var wire 5 D rs2 [4:0] $end
$var wire 5 E rs1 [4:0] $end
$var wire 5 F rd [4:0] $end
$var wire 7 G opcode [6:0] $end
$var wire 32 H instruction [31:0] $end
$var wire 7 I funct7 [6:0] $end
$var wire 3 J funct3 [2:0] $end
$var reg 12 K imm [11:0] $end
$upscope $end
$scope module IMem $end
$var wire 1 ! clk $end
$var wire 32 L instruction [31:0] $end
$var wire 32 M addr [31:0] $end
$upscope $end
$scope module PC $end
$var wire 1 ! clk $end
$var wire 32 N pc_in [31:0] $end
$var wire 1 " reset $end
$var reg 32 O pc_out [31:0] $end
$upscope $end
$scope module RegisterFile $end
$var wire 1 ! clk $end
$var wire 5 P read_reg1 [4:0] $end
$var wire 5 Q read_reg2 [4:0] $end
$var wire 1 # reg_write $end
$var wire 32 R write_data [31:0] $end
$var wire 5 S write_reg [4:0] $end
$var wire 32 T read_data2 [31:0] $end
$var wire 32 U read_data1 [31:0] $end
$var integer 32 V i [31:0] $end
$upscope $end
$upscope $end
$upscope $end
$enddefinitions $end
$comment Show the parameter values. $end
$dumpall
$end
#0
$dumpvars
b100000 V
b0 U
b0 T
b1 S
b1010 R
b1010 Q
b0 P
b0 O
b100 N
b0 M
b101000000000000010010011 L
b1010 K
b0 J
b0 I
b101000000000000010010011 H
b10011 G
b1 F
b0 E
b1010 D
b100000000 C
b0 B
b0 A
0@
0?
b1010 >
b10 =
b0 <
b0 ;
b10011 :
b1010 9
b10 8
b1010 7
b0 6
b1010 5
b1010 4
b0 3
02
b10 1
b1010 0
b0 /
b0 .
b1010 -
b101000000000000010010011 ,
b0 +
b10011 *
b0 )
b1 (
b0 '
b0 &
b0 %
b1010 $
1#
1"
0!
$end
#1
1!
#2
0!
#3
1!
#4
0!
0"
#5
b10100 5
b10100 R
b10100 0
b10100 9
b10100 >
b10100 4
b10100 7
b10 (
b10 F
b10 S
b10100 $
b10100 D
b10100 Q
b10100 -
b10100 K
b1010000000000000100010011 ,
b1010000000000000100010011 H
b1010000000000000100010011 L
b1000 N
b100 )
b100 M
b100 O
1!
#6
0!
#7
b11110 5
b11110 R
b11110 0
b11110 9
b11110 >
b1010 3
b1010 6
b1010 '
b1010 U
b10100 &
b10100 B
b10100 T
b10100 4
b10100 7
b110011 *
b110011 :
b110011 G
b11 (
b11 F
b11 S
b1 %
b1 E
b1 P
b10 $
b10 D
b10 Q
b10 -
b10 K
b1000001000000110110011 ,
b1000001000000110110011 H
b1000001000000110110011 L
b1100 N
b1000 )
b1000 M
b1000 O
1!
#8
0!
#9
b1010 5
b1010 R
b1010 0
b1010 9
b1010 >
b1010 4
b1010 7
b10100 3
b10100 6
b10100 '
b10100 U
b1010 &
b1010 B
b1010 T
b110 1
b110 8
b110 =
b100 (
b100 F
b100 S
b10 %
b10 E
b10 P
b1 $
b1 D
b1 Q
b100000 .
b100000 ;
b100000 I
b10000000001 -
b10000000001 K
b1000000000100010000001000110011 ,
b1000000000100010000001000110011 H
b1000000000100010000001000110011 L
b10000 N
b1100 )
b1100 M
b1100 O
1!
#10
0!
#11
b101 5
b101 R
b101 0
b101 9
b101 >
b0 3
b0 6
b0 '
b0 U
b0 &
b0 B
b0 T
b10 1
b10 8
b10 =
b101 4
b101 7
b10011 *
b10011 :
b10011 G
b1 (
b1 F
b1 S
b0 %
b0 E
b0 P
b101 $
b101 D
b101 Q
b0 .
b0 ;
b0 I
b101 -
b101 K
b10100000000000010010011 ,
b10100000000000010010011 H
b10100000000000010010011 L
b10100 N
b10000 )
b10000 M
b10000 O
1!
#12
0!
#13
b11 5
b11 R
b11 0
b11 9
b11 >
b11110 &
b11110 B
b11110 T
b11 4
b11 7
b10 (
b10 F
b10 S
b11 $
b11 D
b11 Q
b11 -
b11 K
b1100000000000100010011 ,
b1100000000000100010011 H
b1100000000000100010011 L
b11000 N
b10100 )
b10100 M
b10100 O
1!
#14
0!
#15
b1 5
b1 R
b1 0
b1 9
b1 >
b101 3
b101 6
b0 1
b0 8
b0 =
b101 '
b101 U
b11 &
b11 B
b11 T
b11 4
b11 7
b110011 *
b110011 :
b110011 G
b11 (
b11 F
b11 S
b111 /
b111 <
b111 J
b1 %
b1 E
b1 P
b10 $
b10 D
b10 Q
b10 -
b10 K
b1000001111000110110011 ,
b1000001111000110110011 H
b1000001111000110110011 L
b11100 N
b11000 )
b11000 M
b11000 O
1!
#16
0!
#17
b111 5
b111 R
b111 0
b111 9
b111 >
b1 1
b1 8
b1 =
b110 /
b110 <
b110 J
b1000001110000110110011 ,
b1000001110000110110011 H
b1000001110000110110011 L
b100000 N
b11100 )
b11100 M
b11100 O
1!
#18
0!
#19
bx 3
bx 6
bx '
bx U
bx &
bx B
bx T
b1111 1
b1111 8
b1111 =
b0 4
b0 7
x@
x?
bx *
bx :
bx G
bx (
bx F
bx S
bx /
bx <
bx J
bx %
bx E
bx P
bx $
bx D
bx Q
bx .
bx ;
bx I
bx -
bx K
bx ,
bx H
bx L
b100100 N
b100000 )
b100000 M
b100000 O
1!
#20
0!
#21
b101000 N
b100100 )
b100100 M
b100100 O
1!
#22
0!
#23
b101100 N
b101000 )
b101000 M
b101000 O
1!
