src/include/define.vh
`ifndef DEFINES_VH
`define DEFINES_VH

`define OP_IMM    7'b0010011
`define OP_LOAD   7'b0000011
`define OP_STORE  7'b0100011

`endif

src/DMem.v
module DMem(
    input clk,
    input wire [31:0] addr,
    input wire [31:0] write_data,
    input wire mem_read,
    input wire mem_write,
    output wire [31:0] read_data
);

   
    reg [31:0] memory [0:255];

    initial begin 
        for (integer i = 0; i < 256; i = i + 1) begin
            memory[i] = 32'b0;
        end
    end
    
    always @(posedge clk) begin
        if (mem_write) begin
            memory[addr[9:2]] <= write_data;
        end
    end

    assign read_data = memory[addr[9:2]];
endmodule

src/ALU.v
module ALU(
    input wire clk,
    input wire [31:0] operand1,
    input wire [31:0] operand2,
    input wire [3:0] alu_control,
    output reg [31:0] alu_result
);
    always @(*) begin
        case (alu_control)

            4'b0000: alu_result <= operand1 & operand2; 
            4'b0001: alu_result <= operand1 | operand2;
            4'b0010: alu_result <= operand1 + operand2;
            4'b0110: alu_result <= operand1 - operand2;
            4'b0111: alu_result <= (operand1 < operand2);
            4'b1100: alu_result <= ~(operand1 | operand2);
        endcase
    end
endmodule

src/ALUControl.v
module ALUControl(
    input wire clk,
    input wire [1:0] ALUOp,
    input wire [2:0] funct3,
    output reg [3:0] alu_control
);

    always @(*) begin
        if (ALUOp == 2'b00) begin
            alu_control = 4'b0010; // Load/Store: ADD
        end else begin
            case (funct3)
                3'b000: alu_control = 4'b0010; // ADDI
                3'b111: alu_control = 4'b0000; // ANDI
                3'b110: alu_control = 4'b0001; // ORI
                3'b010: alu_control = 4'b0111; // SLTI
            endcase
        end
    end

endmodule

src/RegisterFile.v
module RegisterFile(
    input wire clk,
    input wire [4:0] read_reg1,
    input wire [4:0] read_reg2,
    input wire [4:0] write_reg,
    input wire [31:0] write_data,
    input wire reg_write,   
    output wire [31:0] read_data1,
    output wire [31:0] read_data2
);

    reg [31:0] register[0:31];

    integer i;
    initial begin
        for (i = 0; i < 32; i = i + 1) register[i] = 0;
    end

    always @(posedge clk) begin
    if (reg_write && (write_reg != 5'd0)) begin
        register[write_reg] <= write_data;
    end
    end

    assign read_data1 = (read_reg1 == 5'd0) ? 32'd0 : register[read_reg1];
    assign read_data2 = (read_reg2 == 5'd0) ? 32'd0 : register[read_reg2];

endmodule

src/Decoder.v
module Decoder(
    input wire clk,
    input wire [31:0] instruction,
    output wire [6:0] opcode,
    output wire [4:0] rs1,
    output wire [4:0] rs2,
    output wire [4:0] rd,
    output wire [2:0] funct3,
    output reg [11:0] imm
);
    `include "src/include/define.vh"
    
    assign opcode = instruction[6:0];
    assign rd = instruction[11:7];
    assign funct3 = instruction[14:12];
    assign rs1 = instruction[19:15];
    assign rs2 = instruction[24:20];

    always @(*) begin
        if (opcode == `OP_STORE) begin
            imm = {instruction[31:25], instruction[11:7]};
        end else begin
            imm = instruction[31:20];
        end
    end    
endmodule

src/IMem.v
module IMem(
    input clk,
    input wire [31:0] addr,
    output wire [31:0] instruction
);
    reg [31:0] memory [0:255];
    assign instruction = memory[addr[9:2]];
    

    initial begin
        $readmemh("program/hex/load_store.hex", memory);
    end
    
    
endmodule

src/PC.v
module PC(
    input clk,
    input reset,
    input wire [31:0] pc_in,
    output reg [31:0] pc_out
);
    always @(posedge clk or posedge reset) begin
        if (reset) begin
            pc_out <= 32'b0;
        end else begin
            pc_out <= pc_in;
        end
    end
    
endmodule

src/CPU.v
module CPU(
    input wire clk,
    input wire reset
);

    `include "src/include/define.vh"

    wire [31:0] pc_out;

    PC PC(
        .clk(clk), 
        .reset(reset),
        .pc_in(pc_out + 4),
        .pc_out(pc_out)
    );  

    wire [31:0] instruction;

    IMem IMem(
        .clk(clk),
        .addr(pc_out),
        .instruction(instruction)
    );

    wire [6:0] opcode;
    wire [4:0] rs1;
    wire [4:0] rs2;
    wire [4:0] rd;
    wire [2:0] funct3;
    wire [11:0] imm;

    Decoder Decoder(
        .clk(clk),
        .instruction(instruction),
        .opcode(opcode),
        .rs1(rs1),
        .rs2(rs2),
        .rd(rd),
        .funct3(funct3),
        .imm(imm)
    );

    wire [31:0] reg_read_data1;
    wire [31:0] reg_read_data2;
    reg [31:0] reg_write_data;
    wire reg_write = 1'b1; 
    RegisterFile RegisterFile(
        .clk(clk),
        .read_reg1(rs1),
        .read_reg2(rs2),
        .write_reg(rd),
        .write_data(reg_write_data),
        .reg_write(reg_write),
        .read_data1(reg_read_data1),
        .read_data2(reg_read_data2)
    );

    wire [3:0] alu_control;
    reg [1:0] ALUOp;
    always @(*) begin
        case (opcode)
            `OP_IMM: ALUOp = 2'b10;
            `OP_LOAD:     ALUOp = 2'b00;
            `OP_STORE:    ALUOp = 2'b00;
            default:    ALUOp = 2'b10;
        endcase
    end
    ALUControl ALUControl(
        .clk(clk),
        .ALUOp(ALUOp),
        .funct3(funct3),
        .alu_control(alu_control)
    );


    reg [31:0] alu_input1;
    reg [31:0] alu_input2;
    wire [31:0] alu_result;

    always @(*) begin
        case (opcode) 
            `OP_IMM: begin
                alu_input1 = reg_read_data1;
                alu_input2 = {{20{imm[11]}}, imm};
            end
            `OP_LOAD: begin
                alu_input1 = reg_read_data1;
                alu_input2 = {{20{imm[11]}}, imm};
            end
            `OP_STORE: begin
                alu_input1 = reg_read_data1;
                alu_input2 = {{20{imm[11]}}, imm};
            end
            default: begin
                alu_input1 = reg_read_data1;
                alu_input2 = 32'd0;
            end
        endcase
    end

    ALU ALU(
        .clk(clk),
        .operand1(alu_input1),
        .operand2(alu_input2),
        .alu_control(alu_control),
        .alu_result(alu_result)
    );


    wire [31:0] mem_read_data;
    DMem DMem(
        .clk(clk),
        .addr(alu_result),
        .write_data(reg_read_data2),
        .mem_read(opcode == `OP_LOAD),
        .mem_write(opcode == `OP_STORE),
        .read_data(mem_read_data)
    );


    reg MemtoReg;
    always @(*) begin
        case (opcode)
            `OP_LOAD:    MemtoReg = 1'b1;
            `OP_IMM:  MemtoReg = 1'b0;
            `OP_STORE:      MemtoReg = 1'b0;
            default:     MemtoReg = 1'b0;
        endcase
    end

    always @(*) begin
        reg_write_data = MemtoReg ? mem_read_data : alu_result;
    end

endmodule

tb/CPU_testbench.v
module CPU_testbench;
    reg clk = 0;
    reg reset = 0;

    always #1 begin 
        clk = ~clk;
    end

    initial begin
        $dumpfile("CPU_testbench.vcd");
        $dumpvars(0, CPU_testbench);
    end
    
    CPU CPU(
        .clk(clk),
        .reset(reset)
    );

    initial begin
        reset = 1;
        #4
        reset = 0;
        #20
        $finish;
    end

endmodule

CPU_testbench.vcd
$date
	Tue Jan 13 15:27:42 2026
$end
$version
	Icarus Verilog
$end
$timescale
	1s
$end
$scope module CPU_testbench $end
$var reg 1 ! clk $end
$var reg 1 " reset $end
$scope module CPU $end
$var wire 1 ! clk $end
$var wire 1 # reg_write $end
$var wire 1 " reset $end
$var wire 5 $ rs2 [4:0] $end
$var wire 5 % rs1 [4:0] $end
$var wire 32 & reg_read_data2 [31:0] $end
$var wire 32 ' reg_read_data1 [31:0] $end
$var wire 5 ( rd [4:0] $end
$var wire 32 ) pc_out [31:0] $end
$var wire 7 * opcode [6:0] $end
$var wire 32 + mem_read_data [31:0] $end
$var wire 32 , instruction [31:0] $end
$var wire 12 - imm [11:0] $end
$var wire 3 . funct3 [2:0] $end
$var wire 32 / alu_result [31:0] $end
$var wire 4 0 alu_control [3:0] $end
$var reg 2 1 ALUOp [1:0] $end
$var reg 1 2 MemtoReg $end
$var reg 32 3 alu_input1 [31:0] $end
$var reg 32 4 alu_input2 [31:0] $end
$var reg 32 5 reg_write_data [31:0] $end
$scope module ALU $end
$var wire 1 ! clk $end
$var wire 32 6 operand1 [31:0] $end
$var wire 32 7 operand2 [31:0] $end
$var wire 4 8 alu_control [3:0] $end
$var reg 32 9 alu_result [31:0] $end
$upscope $end
$scope module ALUControl $end
$var wire 2 : ALUOp [1:0] $end
$var wire 1 ! clk $end
$var wire 3 ; funct3 [2:0] $end
$var reg 4 < alu_control [3:0] $end
$upscope $end
$scope module DMem $end
$var wire 32 = addr [31:0] $end
$var wire 1 ! clk $end
$var wire 1 > mem_read $end
$var wire 1 ? mem_write $end
$var wire 32 @ read_data [31:0] $end
$var wire 32 A write_data [31:0] $end
$scope begin $ivl_for_loop0 $end
$var integer 32 B i [31:0] $end
$upscope $end
$upscope $end
$scope module Decoder $end
$var wire 1 ! clk $end
$var wire 5 C rs2 [4:0] $end
$var wire 5 D rs1 [4:0] $end
$var wire 5 E rd [4:0] $end
$var wire 7 F opcode [6:0] $end
$var wire 32 G instruction [31:0] $end
$var wire 3 H funct3 [2:0] $end
$var reg 12 I imm [11:0] $end
$upscope $end
$scope module IMem $end
$var wire 1 ! clk $end
$var wire 32 J instruction [31:0] $end
$var wire 32 K addr [31:0] $end
$upscope $end
$scope module PC $end
$var wire 1 ! clk $end
$var wire 32 L pc_in [31:0] $end
$var wire 1 " reset $end
$var reg 32 M pc_out [31:0] $end
$upscope $end
$scope module RegisterFile $end
$var wire 1 ! clk $end
$var wire 5 N read_reg1 [4:0] $end
$var wire 5 O read_reg2 [4:0] $end
$var wire 1 # reg_write $end
$var wire 32 P write_data [31:0] $end
$var wire 5 Q write_reg [4:0] $end
$var wire 32 R read_data2 [31:0] $end
$var wire 32 S read_data1 [31:0] $end
$var integer 32 T i [31:0] $end
$upscope $end
$upscope $end
$upscope $end
$enddefinitions $end
$comment Show the parameter values. $end
$dumpall
$end
#0
$dumpvars
b100000 T
b0 S
b0 R
b1 Q
b101 P
b101 O
b0 N
b0 M
b100 L
b0 K
b10100000000000010010011 J
b101 I
b0 H
b10100000000000010010011 G
b10011 F
b1 E
b0 D
b101 C
b100000000 B
b0 A
b0 @
0?
0>
b101 =
b10 <
b0 ;
b10 :
b101 9
b10 8
b101 7
b0 6
b101 5
b101 4
b0 3
02
b10 1
b10 0
b101 /
b0 .
b101 -
b10100000000000010010011 ,
b0 +
b10011 *
b0 )
b1 (
b0 '
b0 &
b0 %
b101 $
1#
1"
0!
$end
#1
1!
#2
0!
#3
1!
#4
0!
0"
#5
b110 5
b110 P
b110 /
b110 9
b110 =
b101 3
b101 6
b101 &
b101 A
b101 R
b101 '
b101 S
b1 4
b1 7
b1 $
b1 C
b1 O
b1 %
b1 D
b1 N
b10 (
b10 E
b10 Q
b1 -
b1 I
b100001000000100010011 ,
b100001000000100010011 G
b100001000000100010011 J
b1000 L
b100 )
b100 K
b100 M
1!
#6
0!
#7
b10 5
b10 P
b10 /
b10 9
b10 =
b0 3
b0 6
b0 '
b0 S
b10 4
b10 7
b0 1
b0 :
b10 -
b10 I
b0 %
b0 D
b0 N
b10 .
b10 ;
b10 H
1?
b100011 *
b100011 F
b100000010000100100011 ,
b100000010000100100011 G
b100000010000100100011 J
b1100 L
b1000 )
b1000 K
b1000 M
1!
#8
0!
#9
b101 5
b101 P
b10 &
b10 A
b10 R
12
b10 $
b10 C
b10 O
0?
1>
b11 *
b11 F
b1000000010000100000011 ,
b1000000010000100000011 G
b1000000010000100000011 J
b101 +
b101 @
b10000 L
b1100 )
b1100 K
b1100 M
1!
#10
0!
#11
b0 +
b0 @
b1111 /
b1111 9
b1111 =
b101 3
b101 6
b1111 5
b1111 P
b101 '
b101 S
b10 1
b10 :
02
b1010 4
b1010 7
b1010 $
b1010 C
b1010 O
b10 %
b10 D
b10 N
b0 .
b0 ;
b0 H
b11 (
b11 E
b11 Q
0>
b10011 *
b10011 F
b1010 -
b1010 I
b0 &
b0 A
b0 R
b101000010000000110010011 ,
b101000010000000110010011 G
b101000010000000110010011 J
b10100 L
b10000 )
b10000 K
b10000 M
1!
#12
0!
#13
b101 +
b101 @
b11 5
b11 P
b11 /
b11 9
b11 =
b0 3
b0 6
b1111 &
b1111 A
b1111 R
b0 '
b0 S
b0 1
b0 :
b11 4
b11 7
b11 $
b11 C
b11 O
b0 %
b0 D
b0 N
b10 .
b10 ;
b10 H
1?
b100011 *
b100011 F
b11 -
b11 I
b1100000010000110100011 ,
b1100000010000110100011 G
b1100000010000110100011 J
b11000 L
b10100 )
b10100 K
b10100 M
1!
#14
0!
#15
bx 5
bx P
bx /
bx 9
bx =
bx 3
bx 6
bx '
bx S
b10 1
b10 :
b0 4
b0 7
bx $
bx C
bx O
bx %
bx D
bx N
bx .
bx ;
bx H
bx (
bx E
bx Q
x?
x>
bx *
bx F
bx -
bx I
bx &
bx A
bx R
bx ,
bx G
bx J
bx +
bx @
b11100 L
b11000 )
b11000 K
b11000 M
1!
#16
0!
#17
b100000 L
b11100 )
b11100 K
b11100 M
1!
#18
0!
#19
b100100 L
b100000 )
b100000 K
b100000 M
1!
#20
0!
#21
b101000 L
b100100 )
b100100 K
b100100 M
1!
#22
0!
#23
b101100 L
b101000 )
b101000 K
b101000 M
1!
