src/include/define.vh
`ifndef DEFINES_VH
`define DEFINES_VH

`define OP_IMM    7'b0010011
`define OP_LOAD   7'b0000011
`define OP_STORE  7'b0100011
`define OP_R_TYPE 7'b0110011

`endif

src/DMem.v
module DMem(
    input clk,
    input wire [31:0] addr,
    input wire [31:0] write_data,
    input wire mem_read,
    input wire mem_write,
    output wire [31:0] read_data
);

   
    reg [31:0] memory [0:4095];

    initial begin 
        for (integer i = 0; i < 4096; i = i + 1) begin
            memory[i] = 32'b0;
        end
    end
    
    always @(posedge clk) begin
        if (mem_write) begin
            memory[addr[13:2]] <= write_data;
        end
    end

    assign read_data = (mem_read) ? memory[addr[13:2]] : 32'b0;
endmodule

src/ALU.v
module ALU(
    input wire clk,
    input wire [31:0] operand1,
    input wire [31:0] operand2,
    input wire [3:0] alu_control,
    output reg [31:0] alu_result
);
    always @(*) begin
        case (alu_control)

            4'b0000: alu_result <= operand1 & operand2; 
            4'b0001: alu_result <= operand1 | operand2;
            4'b0010: alu_result <= operand1 + operand2;
            4'b0110: alu_result <= operand1 - operand2;
            4'b0111: alu_result <= (operand1 < operand2);
            4'b1100: alu_result <= ~(operand1 | operand2);
        endcase
    end
endmodule

src/HazardDetectionUnit.v
module HazardDetectionUnit(
    input wire ID_Ex_Mem_Read,
    input wire Ex_Mem_Mem_Read,
    input wire[4:0] ID_Ex_rd,
    input wire[4:0] IF_Id_rs1,
    input wire[4:0] IF_Id_rs2,
    input wire is_branch,
    input wire ID_Ex_Reg_Write,
    input wire Ex_Mem_Reg_Write,
    input wire[4:0] Ex_Mem_rd,
    output wire stall
);
    wire load_use_hazard;
    wire branch_data_hazard;

    assign load_use_hazard = ID_Ex_Mem_Read && (ID_Ex_rd != 5'b0) &&
                   ((ID_Ex_rd == IF_Id_rs1) || (ID_Ex_rd == IF_Id_rs2));
        
    assign branch_data_hazard = is_branch && (
        (ID_Ex_Mem_Read && (ID_Ex_rd != 0) && 
            ((ID_Ex_rd == IF_Id_rs1) || (ID_Ex_rd == IF_Id_rs2))) ||
        (Ex_Mem_Mem_Read && (Ex_Mem_rd != 0) && 
            ((Ex_Mem_rd == IF_Id_rs1) || (Ex_Mem_rd == IF_Id_rs2)))
    );

    assign stall = load_use_hazard || branch_data_hazard;
endmodule

src/RegisterFile.v
module RegisterFile(
    input wire clk,
    input wire [4:0] read_reg1,
    input wire [4:0] read_reg2,
    input wire [4:0] write_reg,
    input wire [31:0] write_data,
    input wire reg_write,   
    output wire [31:0] read_data1,
    output wire [31:0] read_data2
);

    reg [31:0] register[0:31];

    integer i;
    initial begin
        for (i = 0; i < 32; i = i + 1) register[i] = 0;
    end

    always @(posedge clk) begin
    if (reg_write && (write_reg != 5'd0)) begin
        register[write_reg] <= write_data;
    end
    end

    assign read_data1 = (reg_write && (write_reg != 5'd0) && (write_reg == read_reg1)) ? write_data : register[read_reg1];
    assign read_data2 = (reg_write && (write_reg != 5'd0) && (write_reg == read_reg2)) ? write_data : register[read_reg2];

endmodule

src/ALUControl.v
module ALUControl(
    input wire clk,
    input wire [6:0] opcode,
    input wire [6:0] funct7,
    input wire [2:0] funct3,
    output reg [3:0] alu_control
);

    always @(*) begin
        if (opcode == `OP_LOAD || opcode == `OP_STORE) begin
            alu_control = 4'b0010; // Load/Store: ADD
        end else if (opcode == `OP_JAL || opcode == `OP_JALR) begin
            alu_control = 4'b0010; // JAL/JALR: ADD
        end else if (opcode == `OP_IMM) begin
            case (funct3)
                3'b000: alu_control = 4'b0010; // ADDI
                3'b111: alu_control = 4'b0000; // ANDI
                3'b110: alu_control = 4'b0001; // ORI
                3'b010: alu_control = 4'b0111; // SLTI
            endcase
        end else if (opcode == `OP_R_TYPE) begin
            case (funct3)
                3'b000: begin
                    if (funct7 == 7'b0100000) begin
                        alu_control = 4'b0110; // SUB
                    end else begin
                        alu_control = 4'b0010; // ADD
                    end
                end
                3'b111: alu_control = 4'b0000; // AND
                3'b110: alu_control = 4'b0001; // OR
                3'b010: alu_control = 4'b0111; // SLT
            endcase
        end else if (opcode == `OP_BRANCH) begin
            alu_control = 4'b0110; // SUB for branch comparisons
        end else begin
            alu_control = 4'b1111; // NOP or undefined
            
        end
    end

endmodule

src/Decoder.v
module Decoder(
    input wire clk,
    input wire [31:0] instruction,
    output reg [31:0] imm,
    output wire [6:0] funct7,
    output wire [4:0] rs2,
    output wire [4:0] rs1,
    output wire [2:0] funct3,
    output wire [4:0] rd,
    output wire [6:0] opcode
);
    `include "define.vh"
    
    assign funct7 = instruction[31:25];
    assign rs2 = instruction[24:20];
    assign rs1 = instruction[19:15];
    assign funct3 = instruction[14:12];
    assign rd = instruction[11:7];
    assign opcode = instruction[6:0];
    
    always @(*) begin
        case (opcode) 
            `OP_STORE: begin // S-type
                imm = {{20{instruction[31]}}, instruction[31:25], instruction[11:7]}; 
            end
            `OP_BRANCH: begin // B-type
                imm = {{20{instruction[31]}}, instruction[31], instruction[7], instruction[30:25], instruction[11:8], 1'b0};
            end
            `OP_JAL: begin // J-type
                imm = {{12{instruction[31]}}, instruction[31], instruction[19:12], instruction[20], instruction[30:21], 1'b0}; 
            end // I-type
            `OP_LUI, `OP_AUIPC: begin
                imm = {instruction[31:12], 12'b0};
            end
            default: begin
                imm = {{20{instruction[31]}}, instruction[31:20]};
            end
        endcase
    end    
endmodule

src/IMem.v
module IMem(
    input clk,
    input wire [31:0] addr,
    output wire [31:0] instruction
);
    reg [31:0] memory [0:255];
    assign instruction = memory[addr[9:2]];
    

    initial begin
        $readmemh("program/hex/load_store.hex", memory);
    end
    
    
endmodule

src/PC.v
module PC(
    input clk,
    input reset,
    input write_enable,
    input wire [31:0] pc_in,
    output reg [31:0] pc_out
);
    always @(posedge clk or negedge reset) begin
        if (!reset) begin
            pc_out <= 32'b0;
        end else begin
            pc_out <= pc_in;
        end
    end
    
endmodule

src/CPU.v
module CPU(
    input wire clk,
    input wire reset
);

    `include "src/include/define.vh"

    // =========================================================================
    // 1. IF Stage (Instruction Fetch)
    // =========================================================================

    wire [31:0] current_pc;
    reg [31:0] next_pc;
    reg [31:0] next_pc_final;

    PC PC(
        .clk(clk), 
        .reset(reset),
        .write_enable(!stall),
        .pc_in(next_pc_final),
        .pc_out(current_pc)
    );      

    always @(*) begin
        if (stall) begin
            next_pc_final = current_pc;
        end else begin
            next_pc_final = next_pc;
        end
    end
    
    wire [31:0] instruction;

    IMem IMem(
        .clk(clk),
        .addr(current_pc),
        .instruction(instruction)
    );

    // IF/ID Pipeline Register
    reg [31:0] IF_ID_PC;
    reg [31:0] IF_ID_Instruction;


    // =========================================================================
    // 2. ID Stage (Instruction Decode)
    // =========================================================================
    wire [6:0] opcode;
    wire [4:0] rs1, rs2, rd;
    wire [2:0] funct3;
    wire [6:0] funct7;
    wire [31:0] imm;
    wire [3:0] alu_control;
    wire [31:0] reg_read_data1, reg_read_data2;
    
    reg [31:0] reg_write_data;

    Decoder Decoder(
        .clk(clk),
        .instruction(IF_ID_Instruction),
        .imm(imm),
        .funct7(funct7),
        .rs2(rs2),
        .rs1(rs1),
        .funct3(funct3),
        .rd(rd),
        .opcode(opcode)
    );

    ALUControl ALUControl(
        .clk(clk),
        .opcode(opcode),
        .funct7(funct7),
        .funct3(funct3),
        .alu_control(alu_control)
    );


    RegisterFile RegisterFile(
        .clk(clk),
        .read_reg1(rs1),
        .read_reg2(rs2),
        .write_reg(Mem_WB_rd_index),
        .write_data(reg_write_data),
        .reg_write(Mem_WB_Reg_Write),
        .read_data1(reg_read_data1),
        .read_data2(reg_read_data2)
    );

    wire is_branch_instruction = (opcode == `OP_BRANCH) || (opcode == `OP_JAL) || (opcode == `OP_JALR);
    wire stall;

    HazardDetectionUnit HazardDetectionUnit(
        .ID_Ex_Mem_Read(ID_Ex_Mem_Read),
        .Ex_Mem_Mem_Read(Ex_Mem_Mem_Read),
        .ID_Ex_rd(ID_Ex_rd_index),
        .IF_Id_rs1(rs1),
        .IF_Id_rs2(rs2),
        .is_branch(is_branch_instruction),
        .ID_Ex_Reg_Write(ID_Ex_Reg_Write),
        .Ex_Mem_Reg_Write(Ex_Mem_Reg_Write),
        .Ex_Mem_rd(Ex_Mem_rd_index),
        .stall(stall)
    );

    // Control Unit Logic
    reg reg_write_ctrl;
    reg alu_src_ctrl;
    reg mem_to_reg_ctrl;
    reg is_link_control;


    always @(*) begin
        // RegWrite
        case (opcode)
            `OP_R_TYPE, `OP_IMM, `OP_LOAD, `OP_JAL, `OP_JALR: reg_write_ctrl = 1'b1;
            default: reg_write_ctrl = 1'b0;
        endcase

        // ALUSrc
        case (opcode)
            `OP_IMM, `OP_LOAD, `OP_STORE, `OP_JALR: alu_src_ctrl = 1'b1; // immediate
            default: alu_src_ctrl = 1'b0; // register
        endcase

        // MemtoReg
        case (opcode)
            `OP_LOAD: mem_to_reg_ctrl = 1'b1;
            default:  mem_to_reg_ctrl = 1'b0;
        endcase

        // Is Link Control
        case (opcode)
            `OP_JAL, `OP_JALR: is_link_control = 1'b1;
            default: is_link_control = 1'b0;
        endcase
    end

    //Forwarding MUX
    reg [31:0] branch_op1, branch_op2;
    always @(*) begin
        if (ID_Ex_Reg_Write && (ID_Ex_rd_index != 0) && (ID_Ex_rd_index == rs1)) begin
            branch_op1 = alu_result;
        end else if(Ex_Mem_Reg_Write && (Ex_Mem_rd_index != 0) && (Ex_Mem_rd_index == rs1)) begin
            branch_op1 = Ex_Mem_ALU_Result;
        end else begin
            branch_op1 = reg_read_data1;
        end

        if (ID_Ex_Reg_Write && (ID_Ex_rd_index != 0) && (ID_Ex_rd_index == rs2)) begin
            branch_op2 = alu_result;
        end else if(Ex_Mem_Reg_Write && (Ex_Mem_rd_index != 0) && (Ex_Mem_rd_index == rs2)) begin
            branch_op2 = Ex_Mem_ALU_Result;
        end else begin
            branch_op2 = reg_read_data2;
        end
    end
    
    
    // branch jump logic
    reg [31:0] pc_plus_4;
    reg [31:0] pc_branch;
    reg branch_taken;
    wire is_equal = (branch_op1 == branch_op2);
    wire is_less_signed = ($signed(branch_op1) < $signed(branch_op2));
    wire is_less_unsigned = (branch_op1 < branch_op2);


    always @(*) begin
        branch_taken = 1'b0;
        pc_plus_4 = current_pc + 4;
        pc_branch = 32'b0;
        case (opcode)
            `OP_JAL: begin
                branch_taken = 1'b1;
                pc_branch = IF_ID_PC + imm;
            end
            `OP_JALR: begin
                branch_taken = 1'b1;
                pc_branch = (branch_op1 + imm) & ~32'b1;
            end
            `OP_BRANCH: begin
                case (funct3)
                    3'b000: branch_taken = is_equal;        // BEQ
                    3'b001: branch_taken = !is_equal;       // BNE
                    3'b100: branch_taken = is_less_signed;  // BLT
                    3'b101: branch_taken = !is_less_signed; // BGE
                    3'b110: branch_taken = is_less_unsigned;// BLTU
                    3'b111: branch_taken = !is_less_unsigned;// BGEU
                    default: branch_taken = 1'b0;
                endcase
                if (branch_taken) begin
                    pc_branch = IF_ID_PC + imm;
                end
            end
        endcase
        next_pc = branch_taken ? pc_branch : pc_plus_4;
    end


    // ID/Ex Pipeline Register
    reg ID_Ex_Mem_Read, ID_Ex_Mem_Write, ID_Ex_Reg_Write, ID_Ex_Mem_to_Reg;
    reg [31:0] ID_Ex_rs1_data, ID_Ex_rs2_data, ID_Ex_imm, ID_Ex_PC;
    reg [4:0]  ID_Ex_rd_index;
    reg [3:0]  ID_Ex_ALU_Control;
    reg        ID_Ex_ALU_Src, ID_Ex_Is_Link;


    // =========================================================================
    // 3. EX Stage (Execute)
    // =========================================================================
    reg [31:0] alu_input1;
    reg [31:0] alu_input2;
    wire [31:0] alu_result;

    // Forwarding Mux

    reg[1:0] forward_a, forward_b;

    always @(*) begin
        if (Ex_Mem_Reg_Write && (Ex_Mem_rd_index != 0) && (Ex_Mem_rd_index == ID_Ex_rs1_index)) begin
            forward_a = 2'b10;
        end else if (Mem_WB_Reg_Write && (Mem_WB_rd_index != 0) && (Mem_WB_rd_index == ID_Ex_rs1_index)) begin            
            forward_a = 2'b01;
        end else begin
            forward_a = 2'b00;
        end

        if (Ex_Mem_Reg_Write && (Ex_Mem_rd_index != 0) && (Ex_Mem_rd_index == ID_Ex_rs2_index)) begin
            forward_b = 2'b10;
        end else if (Mem_WB_Reg_Write && (Mem_WB_rd_index != 0) && (Mem_WB_rd_index == ID_Ex_rs2_index)) begin
            forward_b = 2'b01;
        end else begin
            forward_b = 2'b00;
        end
    end

    reg [31:0] forwarded_rs2_data;
    always @(*) begin
        case (forward_a)
            2'b00: alu_input1 = ID_Ex_rs1_data;
            2'b10: alu_input1 = Ex_Mem_ALU_Result;
            2'b01: alu_input1 = reg_write_data;
            default: alu_input1 = ID_Ex_rs1_data;
        endcase

        case (forward_b)
            2'b00: forwarded_rs2_data = ID_Ex_rs2_data;
            2'b10: forwarded_rs2_data = Ex_Mem_ALU_Result;
            2'b01: forwarded_rs2_data = reg_write_data;
            default: forwarded_rs2_data = ID_Ex_rs2_data;
        endcase

        alu_input2 = ID_Ex_ALU_Src ? ID_Ex_imm : forwarded_rs2_data;
    end

    ALU ALU(
        .clk(clk),
        .operand1(alu_input1),
        .operand2(alu_input2),
        .alu_control(ID_Ex_ALU_Control),
        .alu_result(alu_result)
    );

    // Ex/Mem Pipeline Register
    reg Ex_Mem_Mem_Read, Ex_Mem_Mem_Write, Ex_Mem_Reg_Write, Ex_Mem_Mem_to_Reg;
    reg [31:0] Ex_Mem_ALU_Result, Ex_Mem_rs2_data;
    reg [4:0]  ID_Ex_rs1_index, ID_Ex_rs2_index, Ex_Mem_rd_index;


    // =========================================================================
    // 4. MEM Stage (Memory Access)
    // =========================================================================
    wire [31:0] mem_read_data;
    DMem DMem(
        .clk(clk),
        .addr(Ex_Mem_ALU_Result),
        .write_data(Ex_Mem_rs2_data),
        .mem_read(Ex_Mem_Mem_Read),
        .mem_write(Ex_Mem_Mem_Write),
        .read_data(mem_read_data)
    );

    // Mem/WB Pipeline Register
    reg Mem_WB_Reg_Write, Mem_WB_Mem_to_Reg;
    reg [31:0] Mem_WB_Read_Data, Mem_WB_ALU_Result;
    reg [4:0]  Mem_WB_rd_index;


    // =========================================================================
    // 5. WB Stage (Write Back)
    // =========================================================================

    always @(*) begin
        reg_write_data = Mem_WB_Mem_to_Reg ? Mem_WB_Read_Data : Mem_WB_ALU_Result;
    end


    // =========================================================================
    // Pipeline Register Update Logic
    // =========================================================================
    always @(posedge clk or negedge reset) begin
        if(!reset) begin
            // IF/ID Pipeline Register
            IF_ID_PC <= 32'b0;
            IF_ID_Instruction <= 32'b0;
            
            // ID/Ex Pipeline Register
            ID_Ex_Mem_Read <= 1'b0;
            ID_Ex_Mem_Write <= 1'b0;
            ID_Ex_Reg_Write <= 1'b0;
            ID_Ex_Mem_to_Reg <= 1'b0;
            ID_Ex_rs1_data <= 32'b0;
            ID_Ex_rs2_data <= 32'b0;
            ID_Ex_imm <= 32'b0;
            ID_Ex_rs1_index <= 5'b0; 
            ID_Ex_rs2_index <= 5'b0;    
            ID_Ex_rd_index <= 5'b0;
            ID_Ex_ALU_Src <= 1'b0;
            ID_Ex_ALU_Control <= 4'b0;
            ID_Ex_PC <= 32'b0;
            ID_Ex_Is_Link <= 1'b0;
            
            // Ex/Mem Pipeline Register
            Ex_Mem_Mem_Read <= 1'b0;
            Ex_Mem_Mem_Write <= 1'b0;
            Ex_Mem_Reg_Write <= 1'b0;
            Ex_Mem_Mem_to_Reg <= 1'b0;
            Ex_Mem_ALU_Result <= 32'b0;
            Ex_Mem_rs2_data <= 32'b0;
            Ex_Mem_rd_index <= 5'b0;
            
            // Mem/WB Pipeline Register
            Mem_WB_Reg_Write <= 1'b0;
            Mem_WB_Mem_to_Reg <= 1'b0;
            Mem_WB_Read_Data <= 32'b0;
            Mem_WB_ALU_Result <= 32'b0;
            Mem_WB_rd_index <= 5'b0;
        end else begin
            // IF/ID Stage
            if (!stall) begin
                if (branch_taken) begin
                    IF_ID_PC <= 32'b0;
                    IF_ID_Instruction <= 32'b0;
                end
                else begin
                    IF_ID_PC <= current_pc;
                    IF_ID_Instruction <= instruction;                    
                end
            end
            
            // ID/Ex Stage
            if (stall) begin
                // Insert Bubble(reset control signals)
                ID_Ex_Mem_Read  <= 1'b0;
                ID_Ex_Mem_Write <= 1'b0;
                ID_Ex_Reg_Write <= 1'b0;
                ID_Ex_Mem_to_Reg <= 1'b0;
                ID_Ex_Is_Link <= 1'b0;

                // reset other signals for debugging clarity
                ID_Ex_rd_index  <= 5'b0;
                ID_Ex_rs1_index <= 5'b0; 
                ID_Ex_rs2_index <= 5'b0;
                ID_Ex_PC <= 32'b0;
            end else begin
                ID_Ex_Mem_Read <= (opcode == `OP_LOAD);
                ID_Ex_Mem_Write <= (opcode == `OP_STORE);
                ID_Ex_Reg_Write <= reg_write_ctrl;
                ID_Ex_Mem_to_Reg <= mem_to_reg_ctrl;
                ID_Ex_rs1_data <= reg_read_data1;
                ID_Ex_rs2_data <= reg_read_data2;
                ID_Ex_imm <= imm;
                ID_Ex_rs1_index <= rs1;
                ID_Ex_rs2_index <= rs2;
                ID_Ex_rd_index <= rd;
                ID_Ex_ALU_Src <= alu_src_ctrl;
                ID_Ex_ALU_Control <= alu_control;
                ID_Ex_PC <= IF_ID_PC;
                ID_Ex_Is_Link <= is_link_control;
            end
            // Ex/Mem Stage
            Ex_Mem_Mem_Read <= ID_Ex_Mem_Read;
            Ex_Mem_Mem_Write <= ID_Ex_Mem_Write;
            Ex_Mem_Reg_Write <= ID_Ex_Reg_Write;
            Ex_Mem_Mem_to_Reg <= ID_Ex_Mem_to_Reg;
            if (ID_Ex_Is_Link) begin
                Ex_Mem_ALU_Result <= ID_Ex_PC + 4; // link address
            end else begin
                Ex_Mem_ALU_Result <= alu_result;
            end
            Ex_Mem_rs2_data <= forwarded_rs2_data;
            Ex_Mem_rd_index <= ID_Ex_rd_index;
            
            // Mem/WB Stage
            Mem_WB_Reg_Write <= Ex_Mem_Reg_Write;
            Mem_WB_Mem_to_Reg <= Ex_Mem_Mem_to_Reg;
            Mem_WB_Read_Data <= mem_read_data;
            Mem_WB_ALU_Result <= Ex_Mem_ALU_Result;
            Mem_WB_rd_index <= Ex_Mem_rd_index;
        end
    end

endmodule

tb/CPU_testbench.v
module CPU_testbench;
    reg clk = 0;
    reg reset = 0;

    always #1 begin 
        clk = ~clk;
    end

    initial begin
        $dumpfile("CPU_testbench.vcd");
        $dumpvars(0, CPU_testbench);
    end
    
    CPU CPU(
        .clk(clk),
        .reset(reset)
    );

    initial begin
        reset = 0;
        #4
        reset = 1;
        #3000
        $finish;
    end

endmodule

CPU_testbench.vcd
$date
	Fri Jan 16 16:29:23 2026
$end
$version
	Icarus Verilog
$end
$timescale
	1s
$end
$scope module CPU_testbench $end
$var reg 1 ! clk $end
$var reg 1 " reset $end
$scope module CPU $end
$var wire 1 ! clk $end
$var wire 1 # is_branch_instruction $end
$var wire 1 " reset $end
$var wire 1 $ stall $end
$var wire 5 % rs2 [4:0] $end
$var wire 5 & rs1 [4:0] $end
$var wire 32 ' reg_read_data2 [31:0] $end
$var wire 32 ( reg_read_data1 [31:0] $end
$var wire 5 ) rd [4:0] $end
$var wire 7 * opcode [6:0] $end
$var wire 32 + mem_read_data [31:0] $end
$var wire 1 , is_less_unsigned $end
$var wire 1 - is_less_signed $end
$var wire 1 . is_equal $end
$var wire 32 / instruction [31:0] $end
$var wire 32 0 imm [31:0] $end
$var wire 7 1 funct7 [6:0] $end
$var wire 3 2 funct3 [2:0] $end
$var wire 32 3 current_pc [31:0] $end
$var wire 32 4 alu_result [31:0] $end
$var wire 4 5 alu_control [3:0] $end
$var reg 32 6 Ex_Mem_ALU_Result [31:0] $end
$var reg 1 7 Ex_Mem_Mem_Read $end
$var reg 1 8 Ex_Mem_Mem_Write $end
$var reg 1 9 Ex_Mem_Mem_to_Reg $end
$var reg 1 : Ex_Mem_Reg_Write $end
$var reg 5 ; Ex_Mem_rd_index [4:0] $end
$var reg 32 < Ex_Mem_rs2_data [31:0] $end
$var reg 4 = ID_Ex_ALU_Control [3:0] $end
$var reg 1 > ID_Ex_ALU_Src $end
$var reg 1 ? ID_Ex_Is_Link $end
$var reg 1 @ ID_Ex_Mem_Read $end
$var reg 1 A ID_Ex_Mem_Write $end
$var reg 1 B ID_Ex_Mem_to_Reg $end
$var reg 32 C ID_Ex_PC [31:0] $end
$var reg 1 D ID_Ex_Reg_Write $end
$var reg 32 E ID_Ex_imm [31:0] $end
$var reg 5 F ID_Ex_rd_index [4:0] $end
$var reg 32 G ID_Ex_rs1_data [31:0] $end
$var reg 5 H ID_Ex_rs1_index [4:0] $end
$var reg 32 I ID_Ex_rs2_data [31:0] $end
$var reg 5 J ID_Ex_rs2_index [4:0] $end
$var reg 32 K IF_ID_Instruction [31:0] $end
$var reg 32 L IF_ID_PC [31:0] $end
$var reg 32 M Mem_WB_ALU_Result [31:0] $end
$var reg 1 N Mem_WB_Mem_to_Reg $end
$var reg 32 O Mem_WB_Read_Data [31:0] $end
$var reg 1 P Mem_WB_Reg_Write $end
$var reg 5 Q Mem_WB_rd_index [4:0] $end
$var reg 32 R alu_input1 [31:0] $end
$var reg 32 S alu_input2 [31:0] $end
$var reg 1 T alu_src_ctrl $end
$var reg 32 U branch_op1 [31:0] $end
$var reg 32 V branch_op2 [31:0] $end
$var reg 1 W branch_taken $end
$var reg 2 X forward_a [1:0] $end
$var reg 2 Y forward_b [1:0] $end
$var reg 32 Z forwarded_rs2_data [31:0] $end
$var reg 1 [ is_link_control $end
$var reg 1 \ mem_to_reg_ctrl $end
$var reg 32 ] next_pc [31:0] $end
$var reg 32 ^ next_pc_final [31:0] $end
$var reg 32 _ pc_branch [31:0] $end
$var reg 32 ` pc_plus_4 [31:0] $end
$var reg 1 a reg_write_ctrl $end
$var reg 32 b reg_write_data [31:0] $end
$scope module ALU $end
$var wire 4 c alu_control [3:0] $end
$var wire 1 ! clk $end
$var wire 32 d operand1 [31:0] $end
$var wire 32 e operand2 [31:0] $end
$var reg 32 f alu_result [31:0] $end
$upscope $end
$scope module ALUControl $end
$var wire 1 ! clk $end
$var wire 7 g opcode [6:0] $end
$var wire 7 h funct7 [6:0] $end
$var wire 3 i funct3 [2:0] $end
$var reg 4 j alu_control [3:0] $end
$upscope $end
$scope module DMem $end
$var wire 32 k addr [31:0] $end
$var wire 1 ! clk $end
$var wire 1 7 mem_read $end
$var wire 1 8 mem_write $end
$var wire 32 l write_data [31:0] $end
$var wire 32 m read_data [31:0] $end
$scope begin $ivl_for_loop0 $end
$var integer 32 n i [31:0] $end
$upscope $end
$upscope $end
$scope module Decoder $end
$var wire 1 ! clk $end
$var wire 32 o instruction [31:0] $end
$var wire 5 p rs2 [4:0] $end
$var wire 5 q rs1 [4:0] $end
$var wire 5 r rd [4:0] $end
$var wire 7 s opcode [6:0] $end
$var wire 7 t funct7 [6:0] $end
$var wire 3 u funct3 [2:0] $end
$var reg 32 v imm [31:0] $end
$upscope $end
$scope module HazardDetectionUnit $end
$var wire 1 7 Ex_Mem_Mem_Read $end
$var wire 1 : Ex_Mem_Reg_Write $end
$var wire 5 w Ex_Mem_rd [4:0] $end
$var wire 1 @ ID_Ex_Mem_Read $end
$var wire 1 D ID_Ex_Reg_Write $end
$var wire 5 x ID_Ex_rd [4:0] $end
$var wire 5 y IF_Id_rs1 [4:0] $end
$var wire 5 z IF_Id_rs2 [4:0] $end
$var wire 1 { branch_data_hazard $end
$var wire 1 # is_branch $end
$var wire 1 | load_use_hazard $end
$var wire 1 $ stall $end
$upscope $end
$scope module IMem $end
$var wire 1 ! clk $end
$var wire 32 } instruction [31:0] $end
$var wire 32 ~ addr [31:0] $end
$upscope $end
$scope module PC $end
$var wire 1 ! clk $end
$var wire 32 !" pc_in [31:0] $end
$var wire 1 " reset $end
$var wire 1 "" write_enable $end
$var reg 32 #" pc_out [31:0] $end
$upscope $end
$scope module RegisterFile $end
$var wire 1 ! clk $end
$var wire 5 $" read_reg1 [4:0] $end
$var wire 5 %" read_reg2 [4:0] $end
$var wire 1 P reg_write $end
$var wire 32 &" write_data [31:0] $end
$var wire 5 '" write_reg [4:0] $end
$var wire 32 (" read_data2 [31:0] $end
$var wire 32 )" read_data1 [31:0] $end
$var integer 32 *" i [31:0] $end
$upscope $end
$upscope $end
$upscope $end
$enddefinitions $end
$comment Show the parameter values. $end
$dumpall
$end
#0
$dumpvars
b100000 *"
b0 )"
b0 ("
b0 '"
b0 &"
b0 %"
b0 $"
b0 #"
1""
b100 !"
b0 ~
b1000000000000000000000100010011 }
0|
0{
b0 z
b0 y
b0 x
b0 w
b0 v
b0 u
b0 t
b0 s
b0 r
b0 q
b0 p
b0 o
b1000000000000 n
b0 m
b0 l
b0 k
b1111 j
b0 i
b0 h
b0 g
b0 f
b0 e
b0 d
b0 c
b0 b
0a
b100 `
b0 _
b100 ^
b100 ]
0\
0[
b0 Z
b0 Y
b0 X
0W
b0 V
b0 U
0T
b0 S
b0 R
b0 Q
0P
b0 O
0N
b0 M
b0 L
b0 K
b0 J
b0 I
b0 H
b0 G
b0 F
b0 E
0D
b0 C
0B
0A
0@
0?
0>
b0 =
b0 <
b0 ;
0:
09
08
07
b0 6
b1111 5
b0 4
b0 3
b0 2
b0 1
b0 0
b1000000000000000000000100010011 /
1.
0-
0,
b0 +
b0 *
b0 )
b0 (
b0 '
b0 &
b0 %
0$
0#
0"
0!
$end
#1
1!
#2
0!
#3
1!
#4
0!
1"
#5
1T
1a
b10 5
b10 j
b10000000000 0
b10000000000 v
b100000 1
b100000 h
b100000 t
b10 )
b10 r
b10011 *
b10011 g
b10011 s
b111100000000000000011101111 /
b111100000000000000011101111 }
b1000 ^
b1000 !"
b1000 ]
b1000 `
b1111 =
b1111 c
b1000000000000000000000100010011 K
b1000000000000000000000100010011 o
b100 3
b100 ~
b100 #"
1!
#6
0!
#7
b10000000000 4
b10000000000 f
1#
1[
0T
b1111100 _
1W
b1100011 /
b1100011 }
b1111100 ^
b1111100 !"
b10000000000 S
b10000000000 e
b1111000 0
b1111000 v
b11 1
b11 h
b11 t
b11000 %
b11000 p
b11000 z
b11000 %"
b1 )
b1 r
b1101111 *
b1101111 g
b1101111 s
b1111100 ]
b1100 `
b1000 3
b1000 ~
b1000 #"
b10 =
b10 c
1>
b10 F
b10 x
b10000000000 E
1D
b111100000000000000011101111 K
b111100000000000000011101111 o
b100 L
1!
#8
0!
#9
b0 4
b0 f
0#
0[
0a
b1111 5
b1111 j
b0 S
b0 e
b0 0
b0 v
b0 1
b0 h
b0 t
b0 %
b0 p
b0 z
b0 %"
b0 )
b0 r
b0 *
b0 g
b0 s
b11111110000000010000000100010011 /
b11111110000000010000000100010011 }
b10000000 ^
b10000000 !"
b10000000 ]
b0 _
b10000000 `
0W
b10 ;
b10 w
b10000000000 6
b10000000000 k
1:
1?
b100 C
0>
b1 F
b1 x
b11000 J
b1111000 E
b0 K
b0 o
b0 L
b1111100 3
b1111100 ~
b1111100 #"
1!
#10
0!
#11
0.
b10000000000 U
b10000000000 (
b10000000000 )"
1T
1a
b10 5
b10 j
b100010010111000100011 /
b100010010111000100011 }
b10000100 ^
b10000100 !"
b10000000000 b
b10000000000 &"
b11111111111111111111111111100000 0
b11111111111111111111111111100000 v
b1111111 1
b1111111 h
b1111111 t
b10 &
b10 q
b10 y
b10 $"
b10 )
b10 r
b10011 *
b10011 g
b10011 s
b10000100 ]
b10000100 `
b10000000 3
b10000000 ~
b10000000 #"
b10 Q
b10 '"
b10000000000 M
1P
b1 ;
b1 w
b1000 6
b1000 k
0?
b0 C
b1111 =
b1111 c
b0 F
b0 x
b0 J
b0 E
0D
b11111110000000010000000100010011 K
b11111110000000010000000100010011 o
b1111100 L
1!
#12
0!
#13
b1111100000 4
b1111100000 f
0-
0,
b1000 V
b1000 '
b1000 ("
0a
b1000 b
b1000 &"
b11111111111111111111111111100000 S
b11111111111111111111111111100000 e
b10000000000 R
b10000000000 d
0.
b1111100000 U
b11100 0
b11100 v
b0 1
b0 h
b0 t
b1 %
b1 p
b1 z
b1 %"
b10 2
b10 i
b10 u
b11100 )
b11100 r
b100011 *
b100011 g
b100011 s
b100000010010110000100011 /
b100000010010110000100011 }
b10001000 ^
b10001000 !"
b10001000 ]
b10001000 `
b1 Q
b1 '"
b1000 M
b0 ;
b0 w
b0 6
b0 k
0:
b1111100 C
b10 =
b10 c
1>
b10 F
b10 x
b10 H
b11111111111111111111111111100000 E
b10000000000 G
1D
b100010010111000100011 K
b100010010111000100011 o
b10000000 L
b10000100 3
b10000100 ~
b10000100 #"
1!
#14
0!
#15
b1111111100 4
b1111111100 f
b0 V
b0 '
b0 ("
b1111100000 R
b1111100000 d
b10000000010000010000010011 /
b10000000010000010000010011 }
b10001100 ^
b10001100 !"
b0 b
b0 &"
b10 X
b11100 S
b11100 e
b1000 Z
b11000 0
b11000 v
b1000 %
b1000 p
b1000 z
b1000 %"
b11000 )
b11000 r
b10001100 ]
b10001100 `
b10001000 3
b10001000 ~
b10001000 #"
b0 Q
b0 '"
b0 M
0P
b10 ;
b10 w
b1111100000 6
b1111100000 k
1:
b10000000 C
b11100 F
b11100 x
b1 J
b11100 E
b1000 I
0D
1A
b100000010010110000100011 K
b100000010010110000100011 o
b10000100 L
1!
#16
0!
