src/include/define.vh
`ifndef DEFINES_VH
`define DEFINES_VH

`define OP_IMM    7'b0010011
`define OP_LOAD   7'b0000011
`define OP_STORE  7'b0100011
`define OP_R_TYPE 7'b0110011
`define OP_BRANCH 7'b1100011
`endif

src/DMem.v
module DMem(
    input clk,
    input wire [31:0] addr,
    input wire [31:0] write_data,
    input wire mem_read,
    input wire mem_write,
    output wire [31:0] read_data
);

   
    reg [31:0] memory [0:4095];

    initial begin 
        for (integer i = 0; i < 4096; i = i + 1) begin
            memory[i] = 32'b0;
        end
    end
    
    always @(posedge clk) begin
        if (mem_write) begin
            memory[addr[13:2]] <= write_data;
        end
    end

    assign read_data = (mem_read) ? memory[addr[13:2]] : 32'b0;
endmodule

src/ALU.v
module ALU(
    input wire clk,
    input wire [31:0] operand1,
    input wire [31:0] operand2,
    input wire [3:0] alu_control,
    output reg [31:0] alu_result
);
    always @(*) begin
        case (alu_control)
            4'b0000: alu_result <= operand1 & operand2; 
            4'b0001: alu_result <= operand1 | operand2;
            4'b0010: alu_result <= operand1 + operand2;
            4'b0110: alu_result <= operand1 - operand2;
            4'b0111: alu_result <= (operand1 < operand2);
            4'b1100: alu_result <= ~(operand1 | operand2);
        endcase
    end
endmodule

src/ALUControl.v
module ALUControl(
    input wire clk,
    input wire [6:0] opcode,
    input wire [6:0] funct7,
    input wire [2:0] funct3,
    output reg [3:0] alu_control
);

    always @(*) begin
        if (opcode == `OP_LOAD || opcode == `OP_STORE) begin
            alu_control = 4'b0010; // Load/Store: ADD
        end else if (opcode == `OP_IMM) begin
            case (funct3)
                3'b000: alu_control = 4'b0010; // ADDI
                3'b111: alu_control = 4'b0000; // ANDI
                3'b110: alu_control = 4'b0001; // ORI
                3'b010: alu_control = 4'b0111; // SLTI
            endcase
        end else if (opcode == `OP_R_TYPE) begin
            case (funct3)
                3'b000: begin
                    if (funct7 == 7'b0100000) begin
                        alu_control = 4'b0110; // SUB
                    end else begin
                        alu_control = 4'b0010; // ADD
                    end
                end
                3'b111: alu_control = 4'b0000; // AND
                3'b110: alu_control = 4'b0001; // OR
                3'b010: alu_control = 4'b0111; // SLT
            endcase
        end else if (opcode == `OP_BRANCH) begin
            case (funct3)
                3'b000: alu_control = 4'b0110; // BEQ
            endcase
        end else begin
            alu_control = 4'b1111; // NOP or undefined
            
        end
    end

endmodule

src/RegisterFile.v
module RegisterFile(
    input wire clk,
    input wire [4:0] read_reg1,
    input wire [4:0] read_reg2,
    input wire [4:0] write_reg,
    input wire [31:0] write_data,
    input wire reg_write,   
    output wire [31:0] read_data1,
    output wire [31:0] read_data2
);

    reg [31:0] register[0:31];

    integer i;
    initial begin
        for (i = 0; i < 32; i = i + 1) register[i] = 0;
    end

    always @(posedge clk) begin
    if (reg_write && (write_reg != 5'd0)) begin
        register[write_reg] <= write_data;
    end
    end

    assign read_data1 = (reg_write && (write_reg != 5'd0) && (write_reg == read_reg1)) ? write_data : register[read_reg1];
    assign read_data2 = (reg_write && (write_reg != 5'd0) && (write_reg == read_reg2)) ? write_data : register[read_reg2];

endmodule

src/Decoder.v
module Decoder(
    input wire clk,
    input wire [31:0] instruction,
    output reg [11:0] imm,
    output wire [6:0] funct7,
    output wire [4:0] rs2,
    output wire [4:0] rs1,
    output wire [2:0] funct3,
    output wire [4:0] rd,
    output wire [6:0] opcode
);
    `include "src/include/define.vh"
    
    assign funct7 = instruction[31:25];
    assign rs2 = instruction[24:20];
    assign rs1 = instruction[19:15];
    assign funct3 = instruction[14:12];
    assign rd = instruction[11:7];
    assign opcode = instruction[6:0];
    
    always @(*) begin
        if (opcode == `OP_STORE) begin
            imm = {instruction[31:25], instruction[11:7]};
        end else if (opcode == `OP_BRANCH) begin
            imm = {instruction[31], instruction[7], instruction[30:25], instruction[11:8]};
        end else begin
            imm = instruction[31:20];
        end
    end    
endmodule

src/IMem.v
module IMem(
    input clk,
    input wire [31:0] addr,
    output wire [31:0] instruction
);
    reg [31:0] memory [0:255];
    assign instruction = memory[addr[9:2]];
    

    initial begin
        $readmemh("program/hex/b_type.hex", memory);
    end
    
    
endmodule

src/PC.v
module PC(
    input clk,
    input reset,
    input wire [31:0] pc_in,
    output reg [31:0] pc_out
);
    always @(posedge clk or posedge reset) begin
        if (reset) begin
            pc_out <= 32'b0;
        end else begin
            pc_out <= pc_in;
        end
    end
    
endmodule

src/CPU.v
module CPU(
    input wire clk,
    input wire reset
);

    `include "src/include/define.vh"

    wire [31:0] current_pc;
    reg [31:0] next_pc;

    PC PC(
        .clk(clk), 
        .reset(reset),
        .pc_in(next_pc),
        .pc_out(current_pc)
    );  

    wire [31:0] instruction;

    IMem IMem(
        .clk(clk),
        .addr(current_pc),
        .instruction(instruction)
    );

    wire [6:0] opcode;
    wire [4:0] rs1;
    wire [4:0] rs2;
    wire [4:0] rd;
    wire [2:0] funct3;
    wire [6:0] funct7;
    wire [11:0] imm;

    Decoder Decoder(
        .clk(clk),
        .instruction(instruction),
        .imm(imm),
        .funct7(funct7),
        .rs2(rs2),
        .rs1(rs1),
        .funct3(funct3),
        .rd(rd),
        .opcode(opcode)
    );

    wire [31:0] reg_read_data1;
    wire [31:0] reg_read_data2;
    reg [31:0] reg_write_data;
    wire reg_write = 1'b1; 
    RegisterFile RegisterFile(
        .clk(clk),
        .read_reg1(rs1),
        .read_reg2(rs2),
        .write_reg(rd),
        .write_data(reg_write_data),
        .reg_write(reg_write),
        .read_data1(reg_read_data1),
        .read_data2(reg_read_data2)
    );

    wire [3:0] alu_control;
    
    ALUControl ALUControl(
        .clk(clk),
        .opcode(opcode),
        .funct7(funct7),
        .funct3(funct3),
        .alu_control(alu_control)
    );


    reg [31:0] alu_input1;
    reg [31:0] alu_input2;
    wire [31:0] alu_result;

    always @(*) begin
        case (opcode) 
            `OP_IMM: begin
                alu_input1 = reg_read_data1;
                alu_input2 = {{20{imm[11]}}, imm};
            end
            `OP_LOAD: begin
                alu_input1 = reg_read_data1;
                alu_input2 = {{20{imm[11]}}, imm};
            end
            `OP_STORE: begin
                alu_input1 = reg_read_data1;
                alu_input2 = {{20{imm[11]}}, imm};
            end
            `OP_R_TYPE: begin
                alu_input1 = reg_read_data1;
                alu_input2 = reg_read_data2;
            end
            `OP_BRANCH: begin
                alu_input1 = reg_read_data1;
                alu_input2 = reg_read_data2;
            end
            default: begin
                alu_input1 = reg_read_data1;
                alu_input2 = 32'd0;
            end
        endcase
    end

    ALU ALU(
        .clk(clk),
        .operand1(alu_input1),
        .operand2(alu_input2),
        .alu_control(alu_control),
        .alu_result(alu_result)
    );


    wire [31:0] mem_read_data;
    DMem DMem(
        .clk(clk),
        .addr(alu_result),
        .write_data(reg_read_data2),
        .mem_read(opcode == `OP_LOAD),
        .mem_write(opcode == `OP_STORE),
        .read_data(mem_read_data)
    );


    reg MemtoReg;
    always @(*) begin
        case (opcode)
            `OP_LOAD:    MemtoReg = 1'b1;
            `OP_IMM:  MemtoReg = 1'b0;
            `OP_STORE:      MemtoReg = 1'b0;
            default:     MemtoReg = 1'b0;
        endcase
    end

    always @(*) begin
        reg_write_data = MemtoReg ? mem_read_data : alu_result;
    end

    reg [31:0] pc_plus_4;
    reg [31:0] pc_branch;
    reg branch_taken;

    always @(*) begin
        pc_plus_4 = current_pc + 4;
        pc_branch = current_pc + {{19{imm[11]}}, imm, 1'b0};
        branch_taken = (opcode == `OP_BRANCH) && (alu_result == 32'b0);
        next_pc = branch_taken ? pc_branch : pc_plus_4;
    end



endmodule

tb/CPU_testbench.v
module CPU_testbench;
    reg clk = 0;
    reg reset = 0;

    always #1 begin 
        clk = ~clk;
    end

    initial begin
        $dumpfile("CPU_testbench.vcd");
        $dumpvars(0, CPU_testbench);
    end
    
    CPU CPU(
        .clk(clk),
        .reset(reset)
    );

    initial begin
        reset = 0;
        #4
        reset = 1;
        #3000
        $finish;
    end

endmodule

CPU_testbench.vcd
$date
	Tue Jan 13 17:50:03 2026
$end
$version
	Icarus Verilog
$end
$timescale
	1s
$end
$scope module CPU_testbench $end
$var reg 1 ! clk $end
$var reg 1 " reset $end
$scope module CPU $end
$var wire 1 ! clk $end
$var wire 1 # reg_write $end
$var wire 1 " reset $end
$var wire 5 $ rs2 [4:0] $end
$var wire 5 % rs1 [4:0] $end
$var wire 32 & reg_read_data2 [31:0] $end
$var wire 32 ' reg_read_data1 [31:0] $end
$var wire 5 ( rd [4:0] $end
$var wire 7 ) opcode [6:0] $end
$var wire 32 * mem_read_data [31:0] $end
$var wire 32 + instruction [31:0] $end
$var wire 12 , imm [11:0] $end
$var wire 7 - funct7 [6:0] $end
$var wire 3 . funct3 [2:0] $end
$var wire 32 / current_pc [31:0] $end
$var wire 32 0 alu_result [31:0] $end
$var wire 4 1 alu_control [3:0] $end
$var reg 1 2 MemtoReg $end
$var reg 32 3 alu_input1 [31:0] $end
$var reg 32 4 alu_input2 [31:0] $end
$var reg 1 5 branch_taken $end
$var reg 32 6 next_pc [31:0] $end
$var reg 32 7 pc_branch [31:0] $end
$var reg 32 8 pc_plus_4 [31:0] $end
$var reg 32 9 reg_write_data [31:0] $end
$scope module ALU $end
$var wire 1 ! clk $end
$var wire 32 : operand1 [31:0] $end
$var wire 32 ; operand2 [31:0] $end
$var wire 4 < alu_control [3:0] $end
$var reg 32 = alu_result [31:0] $end
$upscope $end
$scope module ALUControl $end
$var wire 1 ! clk $end
$var wire 7 > opcode [6:0] $end
$var wire 7 ? funct7 [6:0] $end
$var wire 3 @ funct3 [2:0] $end
$var reg 4 A alu_control [3:0] $end
$upscope $end
$scope module DMem $end
$var wire 32 B addr [31:0] $end
$var wire 1 ! clk $end
$var wire 1 C mem_read $end
$var wire 1 D mem_write $end
$var wire 32 E read_data [31:0] $end
$var wire 32 F write_data [31:0] $end
$scope begin $ivl_for_loop0 $end
$var integer 32 G i [31:0] $end
$upscope $end
$upscope $end
$scope module Decoder $end
$var wire 1 ! clk $end
$var wire 5 H rs2 [4:0] $end
$var wire 5 I rs1 [4:0] $end
$var wire 5 J rd [4:0] $end
$var wire 7 K opcode [6:0] $end
$var wire 32 L instruction [31:0] $end
$var wire 7 M funct7 [6:0] $end
$var wire 3 N funct3 [2:0] $end
$var reg 12 O imm [11:0] $end
$upscope $end
$scope module IMem $end
$var wire 1 ! clk $end
$var wire 32 P instruction [31:0] $end
$var wire 32 Q addr [31:0] $end
$upscope $end
$scope module PC $end
$var wire 1 ! clk $end
$var wire 32 R pc_in [31:0] $end
$var wire 1 " reset $end
$var reg 32 S pc_out [31:0] $end
$upscope $end
$scope module RegisterFile $end
$var wire 1 ! clk $end
$var wire 5 T read_reg1 [4:0] $end
$var wire 5 U read_reg2 [4:0] $end
$var wire 1 # reg_write $end
$var wire 32 V write_data [31:0] $end
$var wire 5 W write_reg [4:0] $end
$var wire 32 X read_data2 [31:0] $end
$var wire 32 Y read_data1 [31:0] $end
$var integer 32 Z i [31:0] $end
$upscope $end
$upscope $end
$upscope $end
$enddefinitions $end
$comment Show the parameter values. $end
$dumpall
$end
#0
$dumpvars
b100000 Z
b0 Y
b0 X
b1 W
b1010 V
b1010 U
b0 T
b0 S
b100 R
b0 Q
b101000000000000010010011 P
b1010 O
b0 N
b0 M
b101000000000000010010011 L
b10011 K
b1 J
b0 I
b1010 H
b100000000 G
b0 F
b0 E
0D
0C
b1010 B
b10 A
b0 @
b0 ?
b10011 >
b1010 =
b10 <
b1010 ;
b0 :
b1010 9
b100 8
b10100 7
b100 6
05
b1010 4
b0 3
02
b10 1
b1010 0
b0 /
b0 .
b0 -
b1010 ,
b101000000000000010010011 +
b0 *
b10011 )
b1 (
b0 '
b0 &
b0 %
b1010 $
1#
1"
0!
$end
#1
1!
#2
0!
#3
1!
#4
0!
0"
#5
b10 (
b10 J
b10 W
b101000000000000100010011 +
b101000000000000100010011 L
b101000000000000100010011 P
b1000 6
b1000 R
b11000 7
b1000 8
b100 /
b100 Q
b100 S
1!
#6
0!
#7
b0 9
b0 V
b0 0
b0 =
b0 B
b0 4
b0 ;
b11 (
b11 J
b11 W
b0 $
b0 H
b0 U
b0 ,
b0 O
b110010011 +
b110010011 L
b110010011 P
b1100 6
b1100 R
b1000 7
b1100 8
b1000 /
b1000 Q
b1000 S
1!
#8
0!
#9
b1010 4
b1010 ;
b1010 3
b1010 :
b110 1
b110 <
b110 A
b1010 '
b1010 Y
b1010 &
b1010 F
b1010 X
15
b1100011 )
b1100011 >
b1100011 K
b1000 (
b1000 J
b1000 W
b1 %
b1 I
b1 T
b10 $
b10 H
b10 U
b100 ,
b100 O
b1000001000010001100011 +
b1000001000010001100011 L
b1000001000010001100011 P
b10100 6
b10100 R
b10100 7
b10000 8
b1100 /
b1100 Q
b1100 S
1!
#10
0!
#11
b1 9
b1 V
b1 0
b1 =
b1 B
b0 3
b0 :
b10 1
b10 <
b10 A
b0 '
b0 Y
b1 4
b1 ;
05
b10011 )
b10011 >
b10011 K
b11 (
b11 J
b11 W
b0 %
b0 I
b0 T
b1 $
b1 H
b1 U
b1 ,
b1 O
b100000000000110010011 +
b100000000000110010011 L
b100000000000110010011 P
b11000 6
b11000 R
b10110 7
b11000 8
b10100 /
b10100 Q
b10100 S
1!
#12
0!
#13
b10 9
b10 V
b10 0
b10 =
b10 B
b10 4
b10 ;
b100 (
b100 J
b100 W
b10 $
b10 H
b10 U
b10 ,
b10 O
b1000000000001000010011 +
b1000000000001000010011 L
b1000000000001000010011 P
b11100 6
b11100 R
b11100 7
b11100 8
b11000 /
b11000 Q
b11000 S
1!
#14
0!
#15
b0 9
b0 V
15
b0 0
b0 =
b0 B
b110 1
b110 <
b110 A
b0 &
b0 F
b0 X
b0 4
b0 ;
b1100011 )
b1100011 >
b1100011 K
b0 (
b0 J
b0 W
b0 $
b0 H
b0 U
b0 ,
b0 O
b1100011 +
b1100011 L
b1100011 P
b11100 6
b11100 R
b11100 7
b100000 8
b11100 /
b11100 Q
b11100 S
1!
