src/include/define.vh
`ifndef DEFINES_VH
`define DEFINES_VH

`define OP_IMM    7'b0010011
`define OP_LOAD   7'b0000011
`define OP_STORE  7'b0100011
`define OP_R_TYPE 7'b0110011

`endif

src/DMem.v
module DMem(
    input clk,
    input wire [31:0] addr,
    input wire [31:0] write_data,
    input wire mem_read,
    input wire mem_write,
    output wire [31:0] read_data
);

   
    reg [31:0] memory [0:4095];

    initial begin 
        for (integer i = 0; i < 4096; i = i + 1) begin
            memory[i] = 32'b0;
        end
    end
    
    always @(posedge clk) begin
        if (mem_write) begin
            memory[addr[13:2]] <= write_data;
        end
    end

    assign read_data = (mem_read) ? memory[addr[13:2]] : 32'b0;
endmodule

src/ALU.v
module ALU(
    input wire clk,
    input wire [31:0] operand1,
    input wire [31:0] operand2,
    input wire [3:0] alu_control,
    output reg [31:0] alu_result
);
    always @(*) begin
        case (alu_control)

            4'b0000: alu_result <= operand1 & operand2; 
            4'b0001: alu_result <= operand1 | operand2;
            4'b0010: alu_result <= operand1 + operand2;
            4'b0110: alu_result <= operand1 - operand2;
            4'b0111: alu_result <= (operand1 < operand2);
            4'b1100: alu_result <= ~(operand1 | operand2);
        endcase
    end
endmodule

src/ALUControl.v
module ALUControl(
    input wire clk,
    input wire [6:0] opcode,
    input wire [6:0] funct7,
    input wire [2:0] funct3,
    output reg [3:0] alu_control
);

    always @(*) begin
        if (opcode == `OP_LOAD || opcode == `OP_STORE) begin
            alu_control = 4'b0010; // Load/Store: ADD
        end else if (opcode == `OP_JAL || opcode == `OP_JALR) begin
            alu_control = 4'b0010; // JAL/JALR: ADD
        end else if (opcode == `OP_IMM) begin
            case (funct3)
                3'b000: alu_control = 4'b0010; // ADDI
                3'b111: alu_control = 4'b0000; // ANDI
                3'b110: alu_control = 4'b0001; // ORI
                3'b010: alu_control = 4'b0111; // SLTI
            endcase
        end else if (opcode == `OP_R_TYPE) begin
            case (funct3)
                3'b000: begin
                    if (funct7 == 7'b0100000) begin
                        alu_control = 4'b0110; // SUB
                    end else begin
                        alu_control = 4'b0010; // ADD
                    end
                end
                3'b111: alu_control = 4'b0000; // AND
                3'b110: alu_control = 4'b0001; // OR
                3'b010: alu_control = 4'b0111; // SLT
            endcase
        end else if (opcode == `OP_BRANCH) begin
            alu_control = 4'b0110; // SUB for branch comparisons
        end else begin
            alu_control = 4'b1111; // NOP or undefined
            
        end
    end

endmodule

src/RegisterFile.v
module RegisterFile(
    input wire clk,
    input wire [4:0] read_reg1,
    input wire [4:0] read_reg2,
    input wire [4:0] write_reg,
    input wire [31:0] write_data,
    input wire reg_write,   
    output wire [31:0] read_data1,
    output wire [31:0] read_data2
);

    reg [31:0] register[0:31];

    integer i;
    initial begin
        for (i = 0; i < 32; i = i + 1) register[i] = 0;
    end

    always @(posedge clk) begin
    if (reg_write && (write_reg != 5'd0)) begin
        register[write_reg] <= write_data;
    end
    end

    assign read_data1 = (reg_write && (write_reg != 5'd0) && (write_reg == read_reg1)) ? write_data : register[read_reg1];
    assign read_data2 = (reg_write && (write_reg != 5'd0) && (write_reg == read_reg2)) ? write_data : register[read_reg2];

endmodule

src/Decoder.v
module Decoder(
    input wire clk,
    input wire [31:0] instruction,
    output reg [31:0] imm,
    output wire [6:0] funct7,
    output wire [4:0] rs2,
    output wire [4:0] rs1,
    output wire [2:0] funct3,
    output wire [4:0] rd,
    output wire [6:0] opcode
);
    `include "define.vh"
    
    assign funct7 = instruction[31:25];
    assign rs2 = instruction[24:20];
    assign rs1 = instruction[19:15];
    assign funct3 = instruction[14:12];
    assign rd = instruction[11:7];
    assign opcode = instruction[6:0];
    
    always @(*) begin
        case (opcode) 
            `OP_STORE: begin // S-type
                imm = {{20{instruction[31]}}, instruction[31:25], instruction[11:7]}; 
            end
            `OP_BRANCH: begin // B-type
                imm = {{20{instruction[31]}}, instruction[31], instruction[7], instruction[30:25], instruction[11:8], 1'b0};
            end
            `OP_JAL: begin // J-type
                imm = {{12{instruction[31]}}, instruction[31], instruction[19:12], instruction[20], instruction[30:21], 1'b0}; 
            end // I-type
            `OP_LUI, `OP_AUIPC: begin
                imm = {instruction[31:12], 12'b0};
            end
            default: begin
                imm = {{20{instruction[31]}}, instruction[31:20]};
            end
        endcase
    end    
endmodule

src/IMem.v
module IMem(
    input clk,
    input wire [31:0] addr,
    output wire [31:0] instruction
);
    reg [31:0] memory [0:4095];
    assign instruction = memory[addr[13:2]];
    

    initial begin
        $readmemh("program/hex/fibonacci.hex", memory);
    end
    
    
endmodule

src/PC.v
module PC(
    input clk,
    input reset,
    input wire [31:0] pc_in,
    output reg [31:0] pc_out
);
    always @(posedge clk or posedge reset) begin
        if (reset) begin
            pc_out <= 32'b0;
        end else begin
            pc_out <= pc_in;
        end
    end
    
endmodule

src/CPU.v
module CPU(
    input wire clk,
    input wire reset
);

    `include "src/include/define.vh"

    wire [31:0] current_pc;
    reg [31:0] next_pc;

    PC PC(
        .clk(clk), 
        .reset(reset),
        .pc_in(next_pc),
        .pc_out(current_pc)
    );  

    wire [31:0] instruction;

    IMem IMem(
        .clk(clk),
        .addr(current_pc),
        .instruction(instruction)
    );

    wire [6:0] opcode;
    wire [4:0] rs1;
    wire [4:0] rs2;
    wire [4:0] rd;
    wire [2:0] funct3;
    wire [6:0] funct7;
    wire [31:0] imm;

    Decoder Decoder(
        .clk(clk),
        .instruction(instruction),
        .imm(imm),
        .funct7(funct7),
        .rs2(rs2),
        .rs1(rs1),
        .funct3(funct3),
        .rd(rd),
        .opcode(opcode)
    );

    wire [31:0] reg_read_data1;
    wire [31:0] reg_read_data2;
    reg [31:0] reg_write_data;
    reg reg_write;
    always @(*) begin
        case (opcode)
            `OP_R_TYPE,
            `OP_IMM,
            `OP_LOAD,
            `OP_JAL,
            `OP_JALR: reg_write = 1'b1;
            `OP_STORE,
            `OP_BRANCH: reg_write = 1'b0;
            default: reg_write = 1'b0;
        endcase
    end
    RegisterFile RegisterFile(
        .clk(clk),
        .read_reg1(rs1),
        .read_reg2(rs2),
        .write_reg(rd),
        .write_data(reg_write_data),
        .reg_write(reg_write),
        .read_data1(reg_read_data1),
        .read_data2(reg_read_data2)
    );

    wire [3:0] alu_control;
    
    ALUControl ALUControl(
        .clk(clk),
        .opcode(opcode),
        .funct7(funct7),
        .funct3(funct3),
        .alu_control(alu_control)
    );


    reg [31:0] alu_input1;
    reg [31:0] alu_input2;
    wire [31:0] alu_result;

    always @(*) begin
        case (opcode) 
            `OP_IMM: begin
                alu_input1 = reg_read_data1;
                alu_input2 = imm;
            end
            `OP_LOAD: begin
                alu_input1 = reg_read_data1;
                alu_input2 = imm;
            end
            `OP_STORE: begin
                alu_input1 = reg_read_data1;
                alu_input2 = imm;
            end
            `OP_R_TYPE: begin
                alu_input1 = reg_read_data1;
                alu_input2 = reg_read_data2;
            end
            `OP_BRANCH: begin
                alu_input1 = reg_read_data1;
                alu_input2 = reg_read_data2;
            end
            `OP_JALR: begin
                alu_input1 = reg_read_data1;
                alu_input2 = imm;
            end
            default: begin
                alu_input1 = reg_read_data1;
                alu_input2 = 32'd0;
            end
        endcase
    end

    ALU ALU(
        .clk(clk),
        .operand1(alu_input1),
        .operand2(alu_input2),
        .alu_control(alu_control),
        .alu_result(alu_result)
    );


    wire [31:0] mem_read_data;
    DMem DMem(
        .clk(clk),
        .addr(alu_result),
        .write_data(reg_read_data2),
        .mem_read(opcode == `OP_LOAD),
        .mem_write(opcode == `OP_STORE),
        .read_data(mem_read_data)
    );


    reg MemtoReg;
    always @(*) begin
        case (opcode)
            `OP_LOAD:    MemtoReg = 1'b1;
            `OP_IMM:  MemtoReg = 1'b0;
            `OP_STORE:      MemtoReg = 1'b0;
            default:     MemtoReg = 1'b0;
        endcase
    end

    always @(*) begin
        case (opcode)
            `OP_JAL,
            `OP_JALR: reg_write_data = pc_plus_4;
            default:
                reg_write_data = MemtoReg ? mem_read_data : alu_result;
        endcase
    end

    reg [31:0] pc_plus_4;
    reg [31:0] pc_branch;
    reg branch_taken;
    wire is_equal = (reg_read_data1 == reg_read_data2);
    wire is_less_signed = ($signed(reg_read_data1) < $signed(reg_read_data2));
    wire is_less_unsigned = (reg_read_data1 < reg_read_data2);


    always @(*) begin
        branch_taken = 1'b0;
        pc_plus_4 = current_pc + 4;
        pc_branch = 32'b0;
        case (opcode)
            `OP_JAL: begin
                branch_taken = 1'b1;
                pc_branch = current_pc + imm;
            end
            `OP_JALR: begin
                branch_taken = 1'b1;
                pc_branch = (reg_read_data1 + imm) & ~32'b1;
            end
            `OP_BRANCH: begin
                case (funct3)
                    3'b000: branch_taken = is_equal;        // BEQ
                    3'b001: branch_taken = !is_equal;       // BNE
                    3'b100: branch_taken = is_less_signed;  // BLT
                    3'b101: branch_taken = !is_less_signed; // BGE
                    3'b110: branch_taken = is_less_unsigned;// BLTU
                    3'b111: branch_taken = !is_less_unsigned;// BGEU
                    default: branch_taken = 1'b0;
                endcase
                if (branch_taken) begin
                    pc_branch = current_pc + imm;
                end
            end
        endcase
        next_pc = branch_taken ? pc_branch : pc_plus_4;
    end



endmodule

tb/CPU_testbench.v
module CPU_testbench;
    reg clk = 0;
    reg reset = 0;

    always #1 begin 
        clk = ~clk;
    end

    initial begin
        $dumpfile("CPU_testbench.vcd");
        $dumpvars(0, CPU_testbench);
    end
    
    CPU CPU(
        .clk(clk),
        .reset(reset)
    );

    initial begin
        reset = 1;
        #4
        reset = 0;
        #3000
        $finish;
    end

endmodule

CPU_testbench.vcd
$date
	Thu Jan 15 16:23:17 2026
$end
$version
	Icarus Verilog
$end
$timescale
	1s
$end
$scope module CPU_testbench $end
$var reg 1 ! clk $end
$var reg 1 " reset $end
$scope module CPU $end
$var wire 1 ! clk $end
$var wire 1 " reset $end
$var wire 5 # rs2 [4:0] $end
$var wire 5 $ rs1 [4:0] $end
$var wire 32 % reg_read_data2 [31:0] $end
$var wire 32 & reg_read_data1 [31:0] $end
$var wire 5 ' rd [4:0] $end
$var wire 7 ( opcode [6:0] $end
$var wire 32 ) mem_read_data [31:0] $end
$var wire 1 * is_less_unsigned $end
$var wire 1 + is_less_signed $end
$var wire 1 , is_equal $end
$var wire 32 - instruction [31:0] $end
$var wire 32 . imm [31:0] $end
$var wire 7 / funct7 [6:0] $end
$var wire 3 0 funct3 [2:0] $end
$var wire 32 1 current_pc [31:0] $end
$var wire 32 2 alu_result [31:0] $end
$var wire 4 3 alu_control [3:0] $end
$var reg 1 4 MemtoReg $end
$var reg 32 5 alu_input1 [31:0] $end
$var reg 32 6 alu_input2 [31:0] $end
$var reg 1 7 branch_taken $end
$var reg 32 8 next_pc [31:0] $end
$var reg 32 9 pc_branch [31:0] $end
$var reg 32 : pc_plus_4 [31:0] $end
$var reg 1 ; reg_write $end
$var reg 32 < reg_write_data [31:0] $end
$scope module ALU $end
$var wire 1 ! clk $end
$var wire 32 = operand1 [31:0] $end
$var wire 32 > operand2 [31:0] $end
$var wire 4 ? alu_control [3:0] $end
$var reg 32 @ alu_result [31:0] $end
$upscope $end
$scope module ALUControl $end
$var wire 1 ! clk $end
$var wire 7 A opcode [6:0] $end
$var wire 7 B funct7 [6:0] $end
$var wire 3 C funct3 [2:0] $end
$var reg 4 D alu_control [3:0] $end
$upscope $end
$scope module DMem $end
$var wire 32 E addr [31:0] $end
$var wire 1 ! clk $end
$var wire 1 F mem_read $end
$var wire 1 G mem_write $end
$var wire 32 H write_data [31:0] $end
$var wire 32 I read_data [31:0] $end
$scope begin $ivl_for_loop0 $end
$var integer 32 J i [31:0] $end
$upscope $end
$upscope $end
$scope module Decoder $end
$var wire 1 ! clk $end
$var wire 5 K rs2 [4:0] $end
$var wire 5 L rs1 [4:0] $end
$var wire 5 M rd [4:0] $end
$var wire 7 N opcode [6:0] $end
$var wire 32 O instruction [31:0] $end
$var wire 7 P funct7 [6:0] $end
$var wire 3 Q funct3 [2:0] $end
$var reg 32 R imm [31:0] $end
$upscope $end
$scope module IMem $end
$var wire 1 ! clk $end
$var wire 32 S instruction [31:0] $end
$var wire 32 T addr [31:0] $end
$upscope $end
$scope module PC $end
$var wire 1 ! clk $end
$var wire 32 U pc_in [31:0] $end
$var wire 1 " reset $end
$var reg 32 V pc_out [31:0] $end
$upscope $end
$scope module RegisterFile $end
$var wire 1 ! clk $end
$var wire 5 W read_reg1 [4:0] $end
$var wire 5 X read_reg2 [4:0] $end
$var wire 1 ; reg_write $end
$var wire 32 Y write_data [31:0] $end
$var wire 5 Z write_reg [4:0] $end
$var wire 32 [ read_data2 [31:0] $end
$var wire 32 \ read_data1 [31:0] $end
$var integer 32 ] i [31:0] $end
$upscope $end
$upscope $end
$upscope $end
$enddefinitions $end
$comment Show the parameter values. $end
$dumpall
$end
#0
$dumpvars
b100000 ]
b0 \
b0 [
b10 Z
b10000000000 Y
b0 X
b0 W
b0 V
b100 U
b0 T
b1000000000000000000000100010011 S
b10000000000 R
b0 Q
b100000 P
b1000000000000000000000100010011 O
b10011 N
b10 M
b0 L
b0 K
b1000000000000 J
b0 I
b0 H
0G
0F
b10000000000 E
b10 D
b0 C
b100000 B
b10011 A
b10000000000 @
b10 ?
b10000000000 >
b0 =
b10000000000 <
1;
b100 :
b0 9
b100 8
07
b10000000000 6
b0 5
04
b10 3
b10000000000 2
b0 1
b0 0
b100000 /
b10000000000 .
b1000000000000000000000100010011 -
1,
0+
0*
b0 )
b10011 (
b10 '
b0 &
b0 %
b0 $
b0 #
1"
0!
$end
#1
1!
#2
0!
#3
1!
#4
0!
0"
#5
b0 2
b0 @
b0 E
b1000 <
b1000 Y
b0 6
b0 >
b1111100 9
17
b1101111 (
b1101111 A
b1101111 N
b1 '
b1 M
b1 Z
b11000 #
b11000 K
b11000 X
b11 /
b11 B
b11 P
b1111000 .
b1111000 R
b111100000000000000011101111 -
b111100000000000000011101111 O
b111100000000000000011101111 S
b1111100 8
b1111100 U
b1000 :
b100 1
b100 T
b100 V
1!
#6
0!
#7
b1111100000 2
b1111100000 @
b1111100000 E
b10000000000 5
b10000000000 =
0,
b10000000000 &
b10000000000 \
b11111111111111111111111111100000 6
b11111111111111111111111111100000 >
b10011 (
b10011 A
b10011 N
b10 '
b10 M
b10 Z
b10 $
b10 L
b10 W
b0 #
b0 K
b0 X
b1111111 /
b1111111 B
b1111111 P
b11111111111111111111111111100000 .
b11111111111111111111111111100000 R
b1111100000 <
b1111100000 Y
b11111110000000010000000100010011 -
b11111110000000010000000100010011 O
b11111110000000010000000100010011 S
b10000000 8
b10000000 U
b0 9
b10000000 :
07
b1111100 1
b1111100 T
b1111100 V
1!
#8
0!
#9
b1111111100 <
b1111111100 Y
b1111111100 2
b1111111100 @
b1111111100 E
0;
b1000 %
b1000 H
b1000 [
b11100 6
b11100 >
b1111100000 5
b1111100000 =
1G
b100011 (
b100011 A
b100011 N
b11100 '
b11100 M
b11100 Z
b10 0
b10 C
b10 Q
b1 #
b1 K
b1 X
b0 /
b0 B
b0 P
b11100 .
b11100 R
b1111100000 &
b1111100000 \
b100010010111000100011 -
b100010010111000100011 O
b100010010111000100011 S
b10000100 8
b10000100 U
b10000100 :
b10000000 1
b10000000 T
b10000000 V
1!
#10
0!
#11
b1111111000 <
b1111111000 Y
b1111111000 2
b1111111000 @
b1111111000 E
b0 %
b0 H
b0 [
b11000 6
b11000 >
b11000 '
b11000 M
b11000 Z
b1000 #
b1000 K
b1000 X
b11000 .
b11000 R
b100000010010110000100011 -
b100000010010110000100011 O
b100000010010110000100011 S
b10001000 8
b10001000 U
b10001000 :
b10000100 1
b10000100 T
b10000100 V
1!
#12
0!
#13
b10000000000 <
b10000000000 Y
b10000000000 2
b10000000000 @
b10000000000 E
1;
b100000 6
b100000 >
0G
b10011 (
b10011 A
b10011 N
b1000 '
b1000 M
b1000 Z
b0 0
b0 C
b0 Q
b0 #
b0 K
b0 X
b1 /
b1 B
b1 P
b100000 .
b100000 R
b10000000010000010000010011 -
b10000000010000010000010011 O
b10000000010000010000010011 S
b10001100 8
b10001100 U
b10001100 :
b10001000 1
b10001000 T
b10001000 V
1!
#14
0!
#15
b111 <
b111 Y
b111 2
b111 @
b111 E
b0 5
b0 =
1,
b0 &
b0 \
b111 6
b111 >
b1010 '
b1010 M
b1010 Z
b0 $
b0 L
b0 W
b111 #
b111 K
b111 X
b0 /
b0 B
b0 P
b111 .
b111 R
b11100000000010100010011 -
b11100000000010100010011 O
b11100000000010100010011 S
b10010000 8
b10010000 U
b10010000 :
b10001100 1
b10001100 T
b10001100 V
1!
#16
0!
#17
b0 2
b0 @
b0 E
b10010100 <
b10010100 Y
b0 6
b0 >
b1100 9
17
b1101111 (
b1101111 A
b1101111 N
b1 '
b1 M
b1 Z
b111 0
b111 C
b111 Q
b11111 $
b11111 L
b11111 W
b11101 #
b11101 K
b11101 X
b1111011 /
b1111011 B
b1111011 P
b11111111111111111111111101111100 .
b11111111111111111111111101111100 R
b11110111110111111111000011101111 -
b11110111110111111111000011101111 O
b11110111110111111111000011101111 S
b1100 8
b1100 U
b10010100 :
b10010000 1
b10010000 T
b10010000 V
1!
#18
0!
#19
b1111000000 2
b1111000000 @
b1111000000 E
b1111100000 5
b1111100000 =
0,
b1111100000 &
b1111100000 \
b11111111111111111111111111100000 6
b11111111111111111111111111100000 >
b10011 (
b10011 A
b10011 N
b10 '
b10 M
b10 Z
b0 0
b0 C
b0 Q
b10 $
b10 L
b10 W
b0 #
b0 K
b0 X
b1111111 /
b1111111 B
b1111111 P
b11111111111111111111111111100000 .
b11111111111111111111111111100000 R
b1111000000 <
b1111000000 Y
b11111110000000010000000100010011 -
b11111110000000010000000100010011 O
b11111110000000010000000100010011 S
b10000 8
b10000 U
b0 9
b10000 :
07
b1100 1
b1100 T
b1100 V
1!
#20
0!
#21
b1111011100 <
b1111011100 Y
b1111011100 2
b1111011100 @
b1111011100 E
0;
b10010100 %
b10010100 H
b10010100 [
b11100 6
b11100 >
b1111000000 5
b1111000000 =
1G
b100011 (
b100011 A
b100011 N
b11100 '
b11100 M
b11100 Z
b10 0
b10 C
b10 Q
b1 #
b1 K
b1 X
b0 /
b0 B
b0 P
b11100 .
b11100 R
b1111000000 &
b1111000000 \
b100010010111000100011 -
b100010010111000100011 O
b100010010111000100011 S
b10100 8
b10100 U
b10100 :
b10000 1
b10000 T
b10000 V
1!
#22
0!
#23
b1111011000 <
b1111011000 Y
b1111011000 2
b1111011000 @
b1111011000 E
1*
1+
b10000000000 %
b10000000000 H
b10000000000 [
b11000 6
b11000 >
b11000 '
b11000 M
b11000 Z
b1000 #
b1000 K
b1000 X
b11000 .
b11000 R
b100000010010110000100011 -
b100000010010110000100011 O
b100000010010110000100011 S
b11000 8
b11000 U
b11000 :
b10100 1
b10100 T
b10100 V
1!
#24
0!
#25
b1111010100 <
b1111010100 Y
b1111010100 2
b1111010100 @
b1111010100 E
0*
0+
b0 %
b0 H
b0 [
b10100 6
b10100 >
b10100 '
b10100 M
b10100 Z
b1001 #
b1001 K
b1001 X
b10100 .
b10100 R
b100100010010101000100011 -
b100100010010101000100011 O
b100100010010101000100011 S
b11100 8
b11100 U
b11100 :
b11000 1
b11000 T
b11000 V
1!
#26
0!
#27
b1111100000 <
b1111100000 Y
b1111100000 2
b1111100000 @
b1111100000 E
1;
b100000 6
b100000 >
0G
b10011 (
b10011 A
b10011 N
b1000 '
b1000 M
b1000 Z
b0 0
b0 C
b0 Q
b0 #
b0 K
b0 X
b1 /
b1 B
b1 P
b100000 .
b100000 R
b10000000010000010000010011 -
b10000000010000010000010011 O
b10000000010000010000010011 S
b100000 8
b100000 U
b100000 :
b11100 1
b11100 T
b11100 V
1!
#28
0!
#29
b1111001100 <
b1111001100 Y
b1111001100 2
b1111001100 @
b1111001100 E
b1111100000 5
b1111100000 =
0;
b1111100000 &
b1111100000 \
b111 %
b111 H
b111 [
b11111111111111111111111111101100 6
b11111111111111111111111111101100 >
1G
b100011 (
b100011 A
b100011 N
b1100 '
b1100 M
b1100 Z
b10 0
b10 C
b10 Q
b1000 $
b1000 L
b1000 W
b1010 #
b1010 K
b1010 X
b1111111 /
b1111111 B
b1111111 P
b11111111111111111111111111101100 .
b11111111111111111111111111101100 R
b11111110101001000010011000100011 -
b11111110101001000010011000100011 O
b11111110101001000010011000100011 S
b100100 8
b100100 U
b100100 :
b100000 1
b100000 T
b100000 V
1!
#30
0!
#31
b1111001100 2
b1111001100 @
b1111001100 E
b111 <
b111 Y
b111 )
b111 I
14
1;
b0 %
b0 H
b0 [
b11111111111111111111111111101100 6
b11111111111111111111111111101100 >
0G
1F
b11 (
b11 A
b11 N
b1110 '
b1110 M
b1110 Z
b1100 #
b1100 K
b1100 X
b11111111111111111111111111101100 .
b11111111111111111111111111101100 R
b11111110110001000010011100000011 -
b11111110110001000010011100000011 O
b11111110110001000010011100000011 S
b101000 8
b101000 U
b101000 :
b100100 1
b100100 T
b100100 V
1!
#32
0!
#33
b1 2
b1 @
b1 E
b1 <
b1 Y
b0 5
b0 =
b0 )
b0 I
04
1*
1+
b0 &
b0 \
b10010100 %
b10010100 H
b10010100 [
b1 6
b1 >
0F
b10011 (
b10011 A
b10011 N
b1111 '
b1111 M
b1111 Z
b0 0
b0 C
b0 Q
b0 $
b0 L
b0 W
b1 #
b1 K
b1 X
b0 /
b0 B
b0 P
b1 .
b1 R
b100000000011110010011 -
b100000000011110010011 O
b100000000011110010011 S
b101100 8
b101100 U
b101100 :
b101000 1
b101000 T
b101000 V
1!
#34
0!
#35
b11111111111111111111111111111010 <
b11111111111111111111111111111010 Y
b11111111111111111111111111111010 2
b11111111111111111111111111111010 @
b11111111111111111111111111111010 E
b1 5
b1 =
0;
b110 3
b110 ?
b110 D
b1 &
b1 \
b111 %
b111 H
b111 [
b111 6
b111 >
b111000 9
17
b1100011 (
b1100011 A
b1100011 N
b1100 '
b1100 M
b1100 Z
b100 0
b100 C
b100 Q
b1111 $
b1111 L
b1111 W
b1110 #
b1110 K
b1110 X
b1100 .
b1100 R
b111001111100011001100011 -
b111001111100011001100011 O
b111001111100011001100011 S
b111000 8
b111000 U
b110000 :
b101100 1
b101100 T
b101100 V
1!
#36
0!
#37
b111 )
b111 I
b1111001100 2
b1111001100 @
b1111001100 E
b111 <
b111 Y
b1111100000 5
b1111100000 =
1;
14
b1111100000 &
b1111100000 \
0*
0+
b0 %
b0 H
b0 [
b10 3
b10 ?
b10 D
b11111111111111111111111111101100 6
b11111111111111111111111111101100 >
1F
b11 (
b11 A
b11 N
b1111 '
b1111 M
b1111 Z
b10 0
b10 C
b10 Q
b1000 $
b1000 L
b1000 W
b1100 #
b1100 K
b1100 X
b1111111 /
b1111111 B
b1111111 P
b11111111111111111111111111101100 .
b11111111111111111111111111101100 R
b11111110110001000010011110000011 -
b11111110110001000010011110000011 O
b11111110110001000010011110000011 S
b111100 8
b111100 U
b0 9
b111100 :
07
b111000 1
b111000 T
b111000 V
1!
#38
0!
#39
b110 2
b110 @
b110 E
b110 <
b110 Y
b111 5
b111 =
b0 )
b0 I
04
b111 &
b111 \
b11111111111111111111111111111111 6
b11111111111111111111111111111111 >
0F
b10011 (
b10011 A
b10011 N
b0 0
b0 C
b0 Q
b1111 $
b1111 L
b1111 W
b11111 #
b11111 K
b11111 X
b11111111111111111111111111111111 .
b11111111111111111111111111111111 R
b11111111111101111000011110010011 -
b11111111111101111000011110010011 O
b11111111111101111000011110010011 S
b1000000 8
b1000000 U
b1000000 :
b111100 1
b111100 T
b111100 V
1!
#40
0!
#41
b0 6
b0 >
b110 5
b110 =
b1010 '
b1010 M
b1010 Z
b0 #
b0 K
b0 X
b0 /
b0 B
b0 P
b0 .
b0 R
b110 &
b110 \
b1111000010100010011 -
b1111000010100010011 O
b1111000010100010011 S
b1000100 8
b1000100 U
b1000100 :
b1000000 1
b1000000 T
b1000000 V
1!
#42
0!
#43
b0 2
b0 @
b0 E
b0 5
b0 =
b1001000 <
b1001000 Y
1,
b0 &
b0 \
b1100 9
17
b1101111 (
b1101111 A
b1101111 N
b1 '
b1 M
b1 Z
b111 0
b111 C
b111 Q
b11111 $
b11111 L
b11111 W
b1001 #
b1001 K
b1001 X
b1111110 /
b1111110 B
b1111110 P
b11111111111111111111111111001000 .
b11111111111111111111111111001000 R
b11111100100111111111000011101111 -
b11111100100111111111000011101111 O
b11111100100111111111000011101111 S
b1100 8
b1100 U
b1001000 :
b1000100 1
b1000100 T
b1000100 V
1!
#44
0!
#45
b1110100000 2
b1110100000 @
b1110100000 E
b1111000000 5
b1111000000 =
0,
b1111000000 &
b1111000000 \
b11111111111111111111111111100000 6
b11111111111111111111111111100000 >
b10011 (
b10011 A
b10011 N
b10 '
b10 M
b10 Z
b0 0
b0 C
b0 Q
b10 $
b10 L
b10 W
b0 #
b0 K
b0 X
b1111111 /
b1111111 B
b1111111 P
b11111111111111111111111111100000 .
b11111111111111111111111111100000 R
b1110100000 <
b1110100000 Y
b11111110000000010000000100010011 -
b11111110000000010000000100010011 O
b11111110000000010000000100010011 S
b10000 8
b10000 U
b0 9
b10000 :
07
b1100 1
b1100 T
b1100 V
1!
#46
0!
#47
b1110111100 <
b1110111100 Y
b1110111100 2
b1110111100 @
b1110111100 E
0;
b1001000 %
b1001000 H
b1001000 [
b11100 6
b11100 >
b1110100000 5
b1110100000 =
1G
b100011 (
b100011 A
b100011 N
b11100 '
b11100 M
b11100 Z
b10 0
b10 C
b10 Q
b1 #
b1 K
b1 X
b0 /
b0 B
b0 P
b11100 .
b11100 R
b1110100000 &
b1110100000 \
b100010010111000100011 -
b100010010111000100011 O
b100010010111000100011 S
b10100 8
b10100 U
b10100 :
b10000 1
b10000 T
b10000 V
1!
#48
0!
#49
b1110111000 <
b1110111000 Y
b1110111000 2
b1110111000 @
b1110111000 E
1*
1+
b1111100000 %
b1111100000 H
b1111100000 [
b11000 6
b11000 >
b11000 '
b11000 M
b11000 Z
b1000 #
b1000 K
b1000 X
b11000 .
b11000 R
b100000010010110000100011 -
b100000010010110000100011 O
b100000010010110000100011 S
b11000 8
b11000 U
b11000 :
b10100 1
b10100 T
b10100 V
1!
#50
0!
#51
b1110110100 <
b1110110100 Y
b1110110100 2
b1110110100 @
b1110110100 E
0*
0+
b0 %
b0 H
b0 [
b10100 6
b10100 >
b10100 '
b10100 M
b10100 Z
b1001 #
b1001 K
b1001 X
b10100 .
b10100 R
b100100010010101000100011 -
b100100010010101000100011 O
b100100010010101000100011 S
b11100 8
b11100 U
b11100 :
b11000 1
b11000 T
b11000 V
1!
#52
0!
#53
b1111000000 <
b1111000000 Y
b1111000000 2
b1111000000 @
b1111000000 E
1;
b100000 6
b100000 >
0G
b10011 (
b10011 A
b10011 N
b1000 '
b1000 M
b1000 Z
b0 0
b0 C
b0 Q
b0 #
b0 K
b0 X
b1 /
b1 B
b1 P
b100000 .
b100000 R
b10000000010000010000010011 -
b10000000010000010000010011 O
b10000000010000010000010011 S
b100000 8
b100000 U
b100000 :
b11100 1
b11100 T
b11100 V
1!
#54
0!
#55
b1110101100 <
b1110101100 Y
b1110101100 2
b1110101100 @
b1110101100 E
b1111000000 5
b1111000000 =
0;
b1111000000 &
b1111000000 \
b110 %
b110 H
b110 [
b11111111111111111111111111101100 6
b11111111111111111111111111101100 >
1G
b100011 (
b100011 A
b100011 N
b1100 '
b1100 M
b1100 Z
b10 0
b10 C
b10 Q
b1000 $
b1000 L
b1000 W
b1010 #
b1010 K
b1010 X
b1111111 /
b1111111 B
b1111111 P
b11111111111111111111111111101100 .
b11111111111111111111111111101100 R
b11111110101001000010011000100011 -
b11111110101001000010011000100011 O
b11111110101001000010011000100011 S
b100100 8
b100100 U
b100100 :
b100000 1
b100000 T
b100000 V
1!
#56
0!
#57
b1110101100 2
b1110101100 @
b1110101100 E
b110 <
b110 Y
b110 )
b110 I
14
1;
b0 %
b0 H
b0 [
b11111111111111111111111111101100 6
b11111111111111111111111111101100 >
0G
1F
b11 (
b11 A
b11 N
b1110 '
b1110 M
b1110 Z
b1100 #
b1100 K
b1100 X
b11111111111111111111111111101100 .
b11111111111111111111111111101100 R
b11111110110001000010011100000011 -
b11111110110001000010011100000011 O
b11111110110001000010011100000011 S
b101000 8
b101000 U
b101000 :
b100100 1
b100100 T
b100100 V
1!
#58
0!
#59
b1 2
b1 @
b1 E
b1 <
b1 Y
b0 5
b0 =
b0 )
b0 I
04
1*
1+
b0 &
b0 \
b1001000 %
b1001000 H
b1001000 [
b1 6
b1 >
0F
b10011 (
b10011 A
b10011 N
b1111 '
b1111 M
b1111 Z
b0 0
b0 C
b0 Q
b0 $
b0 L
b0 W
b1 #
b1 K
b1 X
b0 /
b0 B
b0 P
b1 .
b1 R
b100000000011110010011 -
b100000000011110010011 O
b100000000011110010011 S
b101100 8
b101100 U
b101100 :
b101000 1
b101000 T
b101000 V
1!
#60
0!
#61
b11111111111111111111111111111011 <
b11111111111111111111111111111011 Y
b11111111111111111111111111111011 2
b11111111111111111111111111111011 @
b11111111111111111111111111111011 E
b1 5
b1 =
0;
b110 3
b110 ?
b110 D
b1 &
b1 \
b110 %
b110 H
b110 [
b110 6
b110 >
b111000 9
17
b1100011 (
b1100011 A
b1100011 N
b1100 '
b1100 M
b1100 Z
b100 0
b100 C
b100 Q
b1111 $
b1111 L
b1111 W
b1110 #
b1110 K
b1110 X
b1100 .
b1100 R
b111001111100011001100011 -
b111001111100011001100011 O
b111001111100011001100011 S
b111000 8
b111000 U
b110000 :
b101100 1
b101100 T
b101100 V
1!
#62
0!
