src/include/define.vh
`ifndef DEFINES_VH
`define DEFINES_VH

`define OP_IMM    7'b0010011
`define OP_LOAD   7'b0000011
`define OP_STORE  7'b0100011
`define OP_R_TYPE 7'b0110011

`endif

src/DMem.v
module DMem(
    input clk,
    input wire [31:0] addr,
    input wire [31:0] write_data,
    input wire mem_read,
    input wire mem_write,
    output reg [31:0] read_data
);

   
    reg [31:0] memory [0:4095];

    `ifdef IVARILOG
    initial begin 
        for (integer i = 0; i < 4096; i = i + 1) begin
            memory[i] = 32'b0;
        end
    end
    `endif
    
    always @(negedge clk) begin
        if (mem_write) begin
            memory[addr[13:2]] <= write_data;
        end
        if (mem_read) begin
            read_data <= memory[addr[13:2]];
        end
    end
endmodule

src/ALU.v
module ALU(
    input wire clk,
    input wire [31:0] operand1,
    input wire [31:0] operand2,
    input wire [3:0] alu_control,
    output reg [31:0] alu_result
);
    always @(*) begin
        case (alu_control)

            4'b0000: alu_result <= operand1 & operand2; 
            4'b0001: alu_result <= operand1 | operand2;
            4'b0010: alu_result <= operand1 + operand2;
            4'b0110: alu_result <= operand1 - operand2;
            4'b0111: alu_result <= (operand1 < operand2);
            4'b1100: alu_result <= ~(operand1 | operand2);
        endcase
    end
endmodule

src/HazardDetectionUnit.v
module HazardDetectionUnit(
    input wire ID_Ex_Mem_Read,
    input wire Ex_Mem_Mem_Read,
    input wire[4:0] ID_Ex_rd,
    input wire[4:0] IF_Id_rs1,
    input wire[4:0] IF_Id_rs2,
    input wire is_branch,
    input wire ID_Ex_Reg_Write,
    input wire Ex_Mem_Reg_Write,
    input wire[4:0] Ex_Mem_rd,
    output wire stall
);
    wire load_use_hazard;
    wire branch_data_hazard;

    assign load_use_hazard = ID_Ex_Mem_Read && (ID_Ex_rd != 5'b0) &&
                   ((ID_Ex_rd == IF_Id_rs1) || (ID_Ex_rd == IF_Id_rs2));
        
    assign branch_data_hazard = is_branch && (
        (ID_Ex_Mem_Read && (ID_Ex_rd != 0) && 
            ((ID_Ex_rd == IF_Id_rs1) || (ID_Ex_rd == IF_Id_rs2))) ||
        (Ex_Mem_Mem_Read && (Ex_Mem_rd != 0) && 
            ((Ex_Mem_rd == IF_Id_rs1) || (Ex_Mem_rd == IF_Id_rs2)))
    );

    assign stall = load_use_hazard || branch_data_hazard;
endmodule

src/RegisterFile.v
module RegisterFile(
    input wire clk,
    input wire [4:0] read_reg1,
    input wire [4:0] read_reg2,
    input wire [4:0] write_reg,
    input wire [31:0] write_data,
    input wire reg_write,   
    output wire [31:0] read_data1,
    output wire [31:0] read_data2
);

    reg [31:0] register[0:31];

    integer i;
    initial begin
        for (i = 0; i < 32; i = i + 1) register[i] = 0;
    end

    always @(posedge clk) begin
    if (reg_write && (write_reg != 5'd0)) begin
        register[write_reg] <= write_data;
    end
    end

    assign read_data1 = (reg_write && (write_reg != 5'd0) && (write_reg == read_reg1)) ? write_data : register[read_reg1];
    assign read_data2 = (reg_write && (write_reg != 5'd0) && (write_reg == read_reg2)) ? write_data : register[read_reg2];

endmodule

src/ALUControl.v
module ALUControl(
    input wire clk,
    input wire [6:0] opcode,
    input wire [6:0] funct7,
    input wire [2:0] funct3,
    output reg [3:0] alu_control
);

    always @(*) begin
        if (opcode == `OP_LOAD || opcode == `OP_STORE) begin
            alu_control = 4'b0010; // Load/Store: ADD
        end else if (opcode == `OP_JAL || opcode == `OP_JALR) begin
            alu_control = 4'b0010; // JAL/JALR: ADD
        end else if (opcode == `OP_IMM) begin
            case (funct3)
                3'b000: alu_control = 4'b0010; // ADDI
                3'b111: alu_control = 4'b0000; // ANDI
                3'b110: alu_control = 4'b0001; // ORI
                3'b010: alu_control = 4'b0111; // SLTI
            endcase
        end else if (opcode == `OP_R_TYPE) begin
            case (funct3)
                3'b000: begin
                    if (funct7 == 7'b0100000) begin
                        alu_control = 4'b0110; // SUB
                    end else begin
                        alu_control = 4'b0010; // ADD
                    end
                end
                3'b111: alu_control = 4'b0000; // AND
                3'b110: alu_control = 4'b0001; // OR
                3'b010: alu_control = 4'b0111; // SLT
            endcase
        end else if (opcode == `OP_BRANCH) begin
            alu_control = 4'b0110; // SUB for branch comparisons
        end else begin
            alu_control = 4'b1111; // NOP or undefined
            
        end
    end

endmodule

src/Decoder.v
module Decoder(
    input wire clk,
    input wire [31:0] instruction,
    output reg [31:0] imm,
    output wire [6:0] funct7,
    output wire [4:0] rs2,
    output wire [4:0] rs1,
    output wire [2:0] funct3,
    output wire [4:0] rd,
    output wire [6:0] opcode
);
    `include "define.vh"
    
    assign funct7 = instruction[31:25];
    assign rs2 = instruction[24:20];
    assign rs1 = instruction[19:15];
    assign funct3 = instruction[14:12];
    assign rd = instruction[11:7];
    assign opcode = instruction[6:0];
    
    always @(*) begin
        case (opcode) 
            `OP_STORE: begin // S-type
                imm = {{20{instruction[31]}}, instruction[31:25], instruction[11:7]}; 
            end
            `OP_BRANCH: begin // B-type
                imm = {{20{instruction[31]}}, instruction[31], instruction[7], instruction[30:25], instruction[11:8], 1'b0};
            end
            `OP_JAL: begin // J-type
                imm = {{12{instruction[31]}}, instruction[31], instruction[19:12], instruction[20], instruction[30:21], 1'b0}; 
            end // I-type
            `OP_LUI, `OP_AUIPC: begin
                imm = {instruction[31:12], 12'b0};
            end
            default: begin
                imm = {{20{instruction[31]}}, instruction[31:20]};
            end
        endcase
    end    
endmodule

src/IMem.v
module IMem(
    input clk,
    input wire [31:0] addr,
    output reg [31:0] instruction
);
    reg [31:0] memory [0:4095];

    initial begin
        $readmemh("program/hex/button.hex", memory);
    end
    
    always @(negedge clk) begin
        instruction <= memory[addr[13:2]];
    end
endmodule

src/PC.v
module PC(
    input clk,
    input reset,
    input write_enable,
    input wire [31:0] pc_in,
    output reg [31:0] pc_out
);
    always @(posedge clk or negedge reset) begin
        if (!reset) begin
            pc_out <= 32'b0;
        end else begin
            pc_out <= pc_in;
        end
    end
    
endmodule

src/CPU.v
module CPU(
    input wire clk,
    input wire reset,
    input wire i_button,
    output reg [5:0] o_led
);

    `include "define.vh"

    // =========================================================================
    // 0. Declarations
    // =========================================================================

    // --- Button Synchronization Signals ---
    reg button_sync_0, button_sync_1;

    // --- IF Stage Signals ---
    wire [31:0] current_pc;
    reg [31:0] next_pc;
    reg [31:0] next_pc_final;
    wire [31:0] instruction;
    
    // --- IF/ID Pipeline Register ---
    reg [31:0] IF_ID_PC;
    reg [31:0] IF_ID_Instruction;

    // --- ID Stage Signals ---
    wire [6:0] opcode;
    wire [4:0] rs1, rs2, rd;
    wire [2:0] funct3;
    wire [6:0] funct7;
    wire [31:0] imm;
    wire [3:0] alu_control;
    wire [31:0] reg_read_data1, reg_read_data2;
    reg [31:0] reg_write_data;
    
    // Control Unit Signals
    reg reg_write_ctrl;
    reg alu_src_ctrl;
    reg mem_to_reg_ctrl;
    reg is_link_control;
    reg [1:0] alu_src_a_ctrl;

    
    // Hazard & Branch Logic Signals
    wire stall;          
    reg branch_taken;
    wire is_branch_instruction;
    reg [31:0] pc_plus_4;
    reg [31:0] pc_branch;
    reg [31:0] branch_op1, branch_op2;
    wire is_equal;
    wire is_less_signed;
    wire is_less_unsigned;


    // ---ID/Ex Pipeline Register---
    reg ID_Ex_Reg_Write, ID_Ex_ALU_Src, ID_Ex_Mem_to_Reg, ID_Ex_Is_Link,  ID_Ex_Mem_Read, ID_Ex_Mem_Write;
    reg [1:0] ID_Ex_ALU_Src_A;
    reg [31:0] ID_Ex_rs1_data, ID_Ex_rs2_data, ID_Ex_imm, ID_Ex_PC;
    reg [4:0]  ID_Ex_rd_index, ID_Ex_rs1_index, ID_Ex_rs2_index;
    reg [3:0]  ID_Ex_ALU_Control;


    // --- EX Stage Signals ---
    reg [31:0] alu_input1;
    reg [31:0] alu_input2;
    wire [31:0] alu_result;
    
    // Forwarding Signals
    reg [1:0] forward_a, forward_b;
    reg [31:0] forwarded_rs1_data;
    reg [31:0] forwarded_rs2_data;

    // --- Ex/Mem Pipeline Register ---
    reg Ex_Mem_Mem_Read, Ex_Mem_Mem_Write, Ex_Mem_Reg_Write, Ex_Mem_Mem_to_Reg;
    reg [31:0] Ex_Mem_ALU_Result, Ex_Mem_rs2_data;
    reg [4:0]  Ex_Mem_rd_index;

    // --- MEM Stage Signals ---
    localparam LED_ADDRESS    = 32'h0000007A;
    localparam BUTTON_ADDRESS = 32'h0000007B;
    wire is_led_access;
    wire dmem_write_enable;
    wire [31:0] mem_read_data;

    // --- Mem/WB Pipeline Register ---
    reg Mem_WB_Reg_Write, Mem_WB_Mem_to_Reg;
    reg [31:0] Mem_WB_Read_Data, Mem_WB_ALU_Result;
    reg [4:0]  Mem_WB_rd_index;
    
    always @(posedge clk or negedge reset) begin
        if (!reset) begin
            button_sync_0 <= 1'b1;
            button_sync_1 <= 1'b1;
        end else begin
            button_sync_0 <= i_button;
            button_sync_1 <= button_sync_0;
        end
    end


    PC PC(
        .clk(clk), 
        .reset(reset),
        .write_enable(!stall),
        .pc_in(next_pc_final),
        .pc_out(current_pc)
    );      

    always @(*) begin
        if (stall) begin
            next_pc_final = current_pc;
        end else begin
            next_pc_final = next_pc;
        end
    end
    

    IMem IMem(
        .clk(clk),
        .addr(current_pc),
        .instruction(instruction)
    );


    // =========================================================================
    // 2. ID Stage (Instruction Decode)
    // =========================================================================

    Decoder Decoder(
        .clk(clk),
        .instruction(IF_ID_Instruction),
        .imm(imm),
        .funct7(funct7),
        .rs2(rs2),
        .rs1(rs1),
        .funct3(funct3),
        .rd(rd),
        .opcode(opcode)
    );

    ALUControl ALUControl(
        .clk(clk),
        .opcode(opcode),
        .funct7(funct7),
        .funct3(funct3),
        .alu_control(alu_control)
    );


    RegisterFile RegisterFile(
        .clk(clk),
        .read_reg1(rs1),
        .read_reg2(rs2),
        .write_reg(Mem_WB_rd_index),
        .write_data(reg_write_data),
        .reg_write(Mem_WB_Reg_Write),
        .read_data1(reg_read_data1),
        .read_data2(reg_read_data2)
    );

    assign is_branch_instruction = ((opcode == `OP_BRANCH) || (opcode == `OP_JAL) || (opcode == `OP_JALR));


    HazardDetectionUnit HazardDetectionUnit(
        .ID_Ex_Mem_Read(ID_Ex_Mem_Read),
        .Ex_Mem_Mem_Read(Ex_Mem_Mem_Read),
        .ID_Ex_rd(ID_Ex_rd_index),
        .IF_Id_rs1(rs1),
        .IF_Id_rs2(rs2),
        .is_branch(is_branch_instruction),
        .ID_Ex_Reg_Write(ID_Ex_Reg_Write),
        .Ex_Mem_Reg_Write(Ex_Mem_Reg_Write),
        .Ex_Mem_rd(Ex_Mem_rd_index),
        .stall(stall)
    );

    // Control Unit Logic
    always @(*) begin
        // RegWrite
        case (opcode)
            `OP_R_TYPE, `OP_IMM, `OP_LOAD, `OP_JAL, `OP_JALR, `OP_LUI, `OP_AUIPC: reg_write_ctrl = 1'b1;
            default: reg_write_ctrl = 1'b0;
        endcase

        // ALUSrc
        case (opcode)
            `OP_IMM, `OP_LOAD, `OP_STORE, `OP_LUI, `OP_AUIPC: alu_src_ctrl = 1'b1; // immediate
            default: alu_src_ctrl = 1'b0; // register
        endcase

        // MemtoReg
        case (opcode)
            `OP_LOAD: mem_to_reg_ctrl = 1'b1;
            default:  mem_to_reg_ctrl = 1'b0;
        endcase

        // Is Link Control
        case (opcode)
            `OP_JAL, `OP_JALR: is_link_control = 1'b1;
            default: is_link_control = 1'b0;
        endcase

        // ALUSrcA Control
        case (opcode)
            `OP_AUIPC: alu_src_a_ctrl = 2'b01; // PC
            `OP_LUI:  alu_src_a_ctrl = 2'b10; // Zero
            default:  alu_src_a_ctrl = 2'b00; // rs1
        endcase

    end

    //Forwarding MUX
    always @(*) begin
        if (ID_Ex_Reg_Write && (ID_Ex_rd_index != 0) && (ID_Ex_rd_index == rs1)) begin
            branch_op1 = alu_result;
        end else if(Ex_Mem_Reg_Write && (Ex_Mem_rd_index != 0) && (Ex_Mem_rd_index == rs1)) begin
            branch_op1 = Ex_Mem_ALU_Result;
        end else begin
            branch_op1 = reg_read_data1;
        end

        if (ID_Ex_Reg_Write && (ID_Ex_rd_index != 0) && (ID_Ex_rd_index == rs2)) begin
            branch_op2 = alu_result;
        end else if(Ex_Mem_Reg_Write && (Ex_Mem_rd_index != 0) && (Ex_Mem_rd_index == rs2)) begin
            branch_op2 = Ex_Mem_ALU_Result;
        end else begin
            branch_op2 = reg_read_data2;
        end
    end
    
    
    // branch jump logic
    assign is_equal = (branch_op1 == branch_op2);
    assign is_less_signed = ($signed(branch_op1) < $signed(branch_op2));
    assign is_less_unsigned = (branch_op1 < branch_op2);
    always @(*) begin
        branch_taken = 1'b0;
        pc_plus_4 = current_pc + 4;
        pc_branch = 32'b0;
        case (opcode)
            `OP_JAL: begin
                branch_taken = 1'b1;
                pc_branch = IF_ID_PC + imm;
            end
            `OP_JALR: begin
                branch_taken = 1'b1;
                pc_branch = (branch_op1 + imm) & ~32'b1;
            end
            `OP_BRANCH: begin
                case (funct3)
                    3'b000: branch_taken = is_equal;        // BEQ
                    3'b001: branch_taken = !is_equal;       // BNE
                    3'b100: branch_taken = is_less_signed;  // BLT
                    3'b101: branch_taken = !is_less_signed; // BGE
                    3'b110: branch_taken = is_less_unsigned;// BLTU
                    3'b111: branch_taken = !is_less_unsigned;// BGEU
                    default: branch_taken = 1'b0;
                endcase
                if (branch_taken) begin
                    pc_branch = IF_ID_PC + imm;
                end
            end
        endcase
        next_pc = branch_taken ? pc_branch : pc_plus_4;
    end


    // =========================================================================
    // 3. EX Stage (Execute)
    // =========================================================================

    // Forwarding Mux
    always @(*) begin
        if (Ex_Mem_Reg_Write && (Ex_Mem_rd_index != 0) && (Ex_Mem_rd_index == ID_Ex_rs1_index)) begin
            forward_a = 2'b10;
        end else if (Mem_WB_Reg_Write && (Mem_WB_rd_index != 0) && (Mem_WB_rd_index == ID_Ex_rs1_index)) begin            
            forward_a = 2'b01;
        end else begin
            forward_a = 2'b00;
        end

        if (Ex_Mem_Reg_Write && (Ex_Mem_rd_index != 0) && (Ex_Mem_rd_index == ID_Ex_rs2_index)) begin
            forward_b = 2'b10;
        end else if (Mem_WB_Reg_Write && (Mem_WB_rd_index != 0) && (Mem_WB_rd_index == ID_Ex_rs2_index)) begin
            forward_b = 2'b01;
        end else begin
            forward_b = 2'b00;
        end
    end

    always @(*) begin
        case (forward_a)
            2'b00: forwarded_rs1_data = ID_Ex_rs1_data;
            2'b10: forwarded_rs1_data = Ex_Mem_ALU_Result;
            2'b01: forwarded_rs1_data = reg_write_data;
            default: forwarded_rs1_data = ID_Ex_rs1_data;
        endcase

        case (forward_b)
            2'b00: forwarded_rs2_data = ID_Ex_rs2_data;
            2'b10: forwarded_rs2_data = Ex_Mem_ALU_Result;
            2'b01: forwarded_rs2_data = reg_write_data;
            default: forwarded_rs2_data = ID_Ex_rs2_data;
        endcase

        case (ID_Ex_ALU_Src_A)
            2'b00: alu_input1 = forwarded_rs1_data;
            2'b01: alu_input1 = ID_Ex_PC;   // AUIPC
            2'b10: alu_input1 = 32'b0;    // LUI
            default: alu_input1 = forwarded_rs1_data;
        endcase
        alu_input2 = ID_Ex_ALU_Src ? ID_Ex_imm : forwarded_rs2_data;
    end

    ALU ALU(
        .clk(clk),
        .operand1(alu_input1),
        .operand2(alu_input2),
        .alu_control(ID_Ex_ALU_Control),
        .alu_result(alu_result)
    );


    // =========================================================================
    // 4. MEM Stage (Memory Access)
    // =========================================================================
    assign is_led_access = (Ex_Mem_ALU_Result == LED_ADDRESS);
    assign dmem_write_enable = Ex_Mem_Mem_Write && !is_led_access;

    DMem DMem(
        .clk(clk),
        .addr(Ex_Mem_ALU_Result),
        .write_data(Ex_Mem_rs2_data),
        .mem_read(Ex_Mem_Mem_Read),
        .mem_write(dmem_write_enable),
        .read_data(mem_read_data)
    );

    // MMIO - LED Control
    always @(posedge clk) begin
        if (!reset) begin
            o_led <= 6'b111111;
        end else if (Ex_Mem_Mem_Write && is_led_access) begin
            o_led <= Ex_Mem_rs2_data[5:0];
        end
    end


    // =========================================================================
    // 5. WB Stage (Write Back)
    // =========================================================================

    always @(*) begin
        reg_write_data = Mem_WB_Mem_to_Reg ? Mem_WB_Read_Data : Mem_WB_ALU_Result;
    end


    // =========================================================================
    // Pipeline Register Update Logic
    // =========================================================================
    always @(posedge clk or negedge reset) begin
        if(!reset) begin
            // IF/ID Pipeline Register
            IF_ID_PC <= 32'b0;
            IF_ID_Instruction <= 32'b0;
            
            // ID/Ex Pipeline Register
            ID_Ex_Mem_Read <= 1'b0;
            ID_Ex_Mem_Write <= 1'b0;
            ID_Ex_Reg_Write <= 1'b0;
            ID_Ex_Mem_to_Reg <= 1'b0;
            ID_Ex_rs1_data <= 32'b0;
            ID_Ex_rs2_data <= 32'b0;
            ID_Ex_imm <= 32'b0;
            ID_Ex_rs1_index <= 5'b0; 
            ID_Ex_rs2_index <= 5'b0;    
            ID_Ex_rd_index <= 5'b0;
            ID_Ex_ALU_Src <= 1'b0;
            ID_Ex_ALU_Control <= 4'b0;
            ID_Ex_PC <= 32'b0;
            ID_Ex_Is_Link <= 1'b0;
            
            // Ex/Mem Pipeline Register
            Ex_Mem_Mem_Read <= 1'b0;
            Ex_Mem_Mem_Write <= 1'b0;
            Ex_Mem_Reg_Write <= 1'b0;
            Ex_Mem_Mem_to_Reg <= 1'b0;
            Ex_Mem_ALU_Result <= 32'b0;
            Ex_Mem_rs2_data <= 32'b0;
            Ex_Mem_rd_index <= 5'b0;
            
            // Mem/WB Pipeline Register
            Mem_WB_Reg_Write <= 1'b0;
            Mem_WB_Mem_to_Reg <= 1'b0;
            Mem_WB_Read_Data <= 32'b0;
            Mem_WB_ALU_Result <= 32'b0;
            Mem_WB_rd_index <= 5'b0;
        end else begin
            // IF/ID Stage
            if (!stall) begin
                if (branch_taken) begin
                    IF_ID_PC <= 32'b0;
                    IF_ID_Instruction <= 32'b0;
                end
                else begin
                    IF_ID_PC <= current_pc;
                    IF_ID_Instruction <= instruction;                    
                end
            end
            
            // ID/Ex Stage
            if (stall) begin
                // Insert Bubble(reset control signals)
                ID_Ex_Mem_Read  <= 1'b0;
                ID_Ex_Mem_Write <= 1'b0;
                ID_Ex_Reg_Write <= 1'b0;
                ID_Ex_Mem_to_Reg <= 1'b0;
                ID_Ex_Is_Link <= 1'b0;
                ID_Ex_ALU_Src_A <= 2'b0;

                // reset other signals for debugging clarity
                ID_Ex_rd_index  <= 5'b0;
                ID_Ex_rs1_index <= 5'b0; 
                ID_Ex_rs2_index <= 5'b0;
                ID_Ex_PC <= 32'b0;
            end else begin
                ID_Ex_Mem_Read <= (opcode == `OP_LOAD);
                ID_Ex_Mem_Write <= (opcode == `OP_STORE);
                ID_Ex_Reg_Write <= reg_write_ctrl;
                ID_Ex_Mem_to_Reg <= mem_to_reg_ctrl;
                ID_Ex_rs1_data <= reg_read_data1;
                ID_Ex_rs2_data <= reg_read_data2;
                ID_Ex_imm <= imm;
                ID_Ex_rs1_index <= rs1;
                ID_Ex_rs2_index <= rs2;
                ID_Ex_rd_index <= rd;
                ID_Ex_ALU_Src <= alu_src_ctrl;
                ID_Ex_ALU_Control <= alu_control;
                ID_Ex_PC <= IF_ID_PC;
                ID_Ex_Is_Link <= is_link_control;
                ID_Ex_ALU_Src_A <= alu_src_a_ctrl;
            end
            // Ex/Mem Stage
            Ex_Mem_Mem_Read <= ID_Ex_Mem_Read;
            Ex_Mem_Mem_Write <= ID_Ex_Mem_Write;
            Ex_Mem_Reg_Write <= ID_Ex_Reg_Write;
            Ex_Mem_Mem_to_Reg <= ID_Ex_Mem_to_Reg;
            if (ID_Ex_Is_Link) begin
                Ex_Mem_ALU_Result <= ID_Ex_PC + 4; // link address
            end else begin
                Ex_Mem_ALU_Result <= alu_result;
            end
            Ex_Mem_rs2_data <= forwarded_rs2_data;
            Ex_Mem_rd_index <= ID_Ex_rd_index;
            
            // Mem/WB Stage
            Mem_WB_Reg_Write <= Ex_Mem_Reg_Write;
            Mem_WB_Mem_to_Reg <= Ex_Mem_Mem_to_Reg;
            if (Ex_Mem_ALU_Result == BUTTON_ADDRESS) begin
                Mem_WB_Read_Data <= {31'b0 , ~button_sync_1};
            end else begin
                Mem_WB_Read_Data <= mem_read_data;
            end
            Mem_WB_ALU_Result <= Ex_Mem_ALU_Result;
            Mem_WB_rd_index <= Ex_Mem_rd_index;
        end
    end

endmodule

tb/CPU_testbench.v
module CPU_testbench;
    reg clk = 0;
    reg reset = 0;
    wire [5:0] o_led;
    reg i_button = 1;

    always #1 begin 
        clk = ~clk;
    end

    initial begin
        $dumpfile("CPU_testbench.vcd");
        $dumpvars(0, CPU_testbench);
    end
    
    CPU CPU(
        .clk(clk),
        .reset(reset),
        .i_button(i_button),
        .o_led(o_led)
    );
    
    initial begin
        reset = 0;
        #10
        reset = 1;
        #1000
        i_button = 0;
        #200
        $finish;
    end

endmodule

CPU_testbench.vcd
$date
	Tue Jan 27 11:23:41 2026
$end
$version
	Icarus Verilog
$end
$timescale
	1s
$end
$scope module CPU_testbench $end
$var wire 6 ! o_led [5:0] $end
$var reg 1 " clk $end
$var reg 1 # i_button $end
$var reg 1 $ reset $end
$scope module CPU $end
$var wire 1 " clk $end
$var wire 1 % dmem_write_enable $end
$var wire 1 # i_button $end
$var wire 1 & is_branch_instruction $end
$var wire 1 $ reset $end
$var wire 1 ' stall $end
$var wire 5 ( rs2 [4:0] $end
$var wire 5 ) rs1 [4:0] $end
$var wire 32 * reg_read_data2 [31:0] $end
$var wire 32 + reg_read_data1 [31:0] $end
$var wire 5 , rd [4:0] $end
$var wire 7 - opcode [6:0] $end
$var wire 32 . mem_read_data [31:0] $end
$var wire 1 / is_less_unsigned $end
$var wire 1 0 is_less_signed $end
$var wire 1 1 is_led_access $end
$var wire 1 2 is_equal $end
$var wire 32 3 instruction [31:0] $end
$var wire 32 4 imm [31:0] $end
$var wire 7 5 funct7 [6:0] $end
$var wire 3 6 funct3 [2:0] $end
$var wire 32 7 current_pc [31:0] $end
$var wire 32 8 alu_result [31:0] $end
$var wire 4 9 alu_control [3:0] $end
$var parameter 32 : BUTTON_ADDRESS $end
$var parameter 32 ; LED_ADDRESS $end
$var reg 32 < Ex_Mem_ALU_Result [31:0] $end
$var reg 1 = Ex_Mem_Mem_Read $end
$var reg 1 > Ex_Mem_Mem_Write $end
$var reg 1 ? Ex_Mem_Mem_to_Reg $end
$var reg 1 @ Ex_Mem_Reg_Write $end
$var reg 5 A Ex_Mem_rd_index [4:0] $end
$var reg 32 B Ex_Mem_rs2_data [31:0] $end
$var reg 4 C ID_Ex_ALU_Control [3:0] $end
$var reg 1 D ID_Ex_ALU_Src $end
$var reg 2 E ID_Ex_ALU_Src_A [1:0] $end
$var reg 1 F ID_Ex_Is_Link $end
$var reg 1 G ID_Ex_Mem_Read $end
$var reg 1 H ID_Ex_Mem_Write $end
$var reg 1 I ID_Ex_Mem_to_Reg $end
$var reg 32 J ID_Ex_PC [31:0] $end
$var reg 1 K ID_Ex_Reg_Write $end
$var reg 32 L ID_Ex_imm [31:0] $end
$var reg 5 M ID_Ex_rd_index [4:0] $end
$var reg 32 N ID_Ex_rs1_data [31:0] $end
$var reg 5 O ID_Ex_rs1_index [4:0] $end
$var reg 32 P ID_Ex_rs2_data [31:0] $end
$var reg 5 Q ID_Ex_rs2_index [4:0] $end
$var reg 32 R IF_ID_Instruction [31:0] $end
$var reg 32 S IF_ID_PC [31:0] $end
$var reg 32 T Mem_WB_ALU_Result [31:0] $end
$var reg 1 U Mem_WB_Mem_to_Reg $end
$var reg 32 V Mem_WB_Read_Data [31:0] $end
$var reg 1 W Mem_WB_Reg_Write $end
$var reg 5 X Mem_WB_rd_index [4:0] $end
$var reg 32 Y alu_input1 [31:0] $end
$var reg 32 Z alu_input2 [31:0] $end
$var reg 2 [ alu_src_a_ctrl [1:0] $end
$var reg 1 \ alu_src_ctrl $end
$var reg 32 ] branch_op1 [31:0] $end
$var reg 32 ^ branch_op2 [31:0] $end
$var reg 1 _ branch_taken $end
$var reg 1 ` button_sync_0 $end
$var reg 1 a button_sync_1 $end
$var reg 2 b forward_a [1:0] $end
$var reg 2 c forward_b [1:0] $end
$var reg 32 d forwarded_rs1_data [31:0] $end
$var reg 32 e forwarded_rs2_data [31:0] $end
$var reg 1 f is_link_control $end
$var reg 1 g mem_to_reg_ctrl $end
$var reg 32 h next_pc [31:0] $end
$var reg 32 i next_pc_final [31:0] $end
$var reg 6 j o_led [5:0] $end
$var reg 32 k pc_branch [31:0] $end
$var reg 32 l pc_plus_4 [31:0] $end
$var reg 1 m reg_write_ctrl $end
$var reg 32 n reg_write_data [31:0] $end
$scope module ALU $end
$var wire 4 o alu_control [3:0] $end
$var wire 1 " clk $end
$var wire 32 p operand1 [31:0] $end
$var wire 32 q operand2 [31:0] $end
$var reg 32 r alu_result [31:0] $end
$upscope $end
$scope module ALUControl $end
$var wire 1 " clk $end
$var wire 7 s opcode [6:0] $end
$var wire 7 t funct7 [6:0] $end
$var wire 3 u funct3 [2:0] $end
$var reg 4 v alu_control [3:0] $end
$upscope $end
$scope module DMem $end
$var wire 32 w addr [31:0] $end
$var wire 1 " clk $end
$var wire 1 = mem_read $end
$var wire 1 % mem_write $end
$var wire 32 x write_data [31:0] $end
$var reg 32 y read_data [31:0] $end
$scope begin $ivl_for_loop0 $end
$var integer 32 z i [31:0] $end
$upscope $end
$upscope $end
$scope module Decoder $end
$var wire 1 " clk $end
$var wire 32 { instruction [31:0] $end
$var wire 5 | rs2 [4:0] $end
$var wire 5 } rs1 [4:0] $end
$var wire 5 ~ rd [4:0] $end
$var wire 7 !" opcode [6:0] $end
$var wire 7 "" funct7 [6:0] $end
$var wire 3 #" funct3 [2:0] $end
$var reg 32 $" imm [31:0] $end
$upscope $end
$scope module HazardDetectionUnit $end
$var wire 1 = Ex_Mem_Mem_Read $end
$var wire 1 @ Ex_Mem_Reg_Write $end
$var wire 5 %" Ex_Mem_rd [4:0] $end
$var wire 1 G ID_Ex_Mem_Read $end
$var wire 1 K ID_Ex_Reg_Write $end
$var wire 5 &" ID_Ex_rd [4:0] $end
$var wire 5 '" IF_Id_rs1 [4:0] $end
$var wire 5 (" IF_Id_rs2 [4:0] $end
$var wire 1 )" branch_data_hazard $end
$var wire 1 & is_branch $end
$var wire 1 *" load_use_hazard $end
$var wire 1 ' stall $end
$upscope $end
$scope module IMem $end
$var wire 1 " clk $end
$var wire 32 +" addr [31:0] $end
$var reg 32 ," instruction [31:0] $end
$upscope $end
$scope module PC $end
$var wire 1 " clk $end
$var wire 32 -" pc_in [31:0] $end
$var wire 1 $ reset $end
$var wire 1 ." write_enable $end
$var reg 32 /" pc_out [31:0] $end
$upscope $end
$scope module RegisterFile $end
$var wire 1 " clk $end
$var wire 5 0" read_reg1 [4:0] $end
$var wire 5 1" read_reg2 [4:0] $end
$var wire 1 W reg_write $end
$var wire 32 2" write_data [31:0] $end
$var wire 5 3" write_reg [4:0] $end
$var wire 32 4" read_data2 [31:0] $end
$var wire 32 5" read_data1 [31:0] $end
$var integer 32 6" i [31:0] $end
$upscope $end
$upscope $end
$upscope $end
$enddefinitions $end
$comment Show the parameter values. $end
$dumpall
b1111010 ;
b1111011 :
$end
#0
$dumpvars
b100000 6"
b0 5"
b0 4"
b0 3"
b0 2"
b0 1"
b0 0"
b0 /"
1."
b100 -"
bx ,"
b0 +"
0*"
0)"
b0 ("
b0 '"
b0 &"
b0 %"
b0 $"
b0 #"
b0 ""
b0 !"
b0 ~
b0 }
b0 |
b0 {
b1000000000000 z
bx y
b0 x
b0 w
b1111 v
b0 u
b0 t
b0 s
b0 r
b0 q
b0 p
b0 o
b0 n
0m
b100 l
b0 k
bx j
b100 i
b100 h
0g
0f
b0 e
b0 d
b0 c
b0 b
1a
1`
0_
b0 ^
b0 ]
0\
b0 [
b0 Z
b0 Y
b0 X
0W
b0 V
0U
b0 T
b0 S
b0 R
b0 Q
b0 P
b0 O
b0 N
b0 M
b0 L
0K
b0 J
0I
0H
0G
0F
bx E
0D
b0 C
b0 B
b0 A
0@
0?
0>
0=
b0 <
b1111 9
b0 8
b0 7
b0 6
b0 5
b0 4
bx 3
12
01
00
0/
bx .
b0 -
b0 ,
b0 +
b0 *
b0 )
b0 (
0'
0&
0%
0$
1#
0"
bx !
$end
#1
b111111 !
b111111 j
1"
#2
b1000000000000000000000100010011 3
b1000000000000000000000100010011 ,"
0"
#3
1"
#4
0"
#5
1"
#6
0"
#7
1"
#8
0"
#9
1"
#10
0"
1$
#11
1\
1m
b10 9
b10 v
b1000 i
b1000 -"
b1000 h
b1000 l
b10000000000 4
b10000000000 $"
b100000 5
b100000 t
b100000 ""
b10 ,
b10 ~
b10011 -
b10011 s
b10011 !"
b100 7
b100 +"
b100 /"
bx V
b0 E
b1111 C
b1111 o
b1000000000000000000000100010011 R
b1000000000000000000000100010011 {
1"
#12
b100000000000000011101111 3
b100000000000000011101111 ,"
0"
#13
b10000000000 8
b10000000000 r
1&
1f
0\
b1100 k
1_
b10000000000 Z
b10000000000 q
b1000 4
b1000 $"
b0 5
b0 t
b0 ""
b1000 (
b1000 |
b1000 ("
b1000 1"
b1 ,
b1 ~
b1101111 -
b1101111 s
b1101111 !"
b1100 i
b1100 -"
b1100 h
b1100 l
b10 C
b10 o
1D
b10 M
b10 &"
b10000000000 L
1K
b100000000000000011101111 R
b100000000000000011101111 {
b100 S
b1000 7
b1000 +"
b1000 /"
1"
#14
b1100011 3
b1100011 ,"
0"
