src/ALU.v
module ALU(
    input wire clk,
    input wire [31:0] operand1,
    input wire [31:0] operand2,
    input wire [3:0] alu_control,
    output reg [31:0] alu_result
);
    always @(*) begin // Combinational logic
        case (alu_control)

            4'b0000: alu_result <= operand1 & operand2; 
            4'b0001: alu_result <= operand1 | operand2;
            4'b0010: alu_result <= operand1 + operand2;
            4'b0110: alu_result <= operand1 - operand2;
            4'b0111: alu_result <= (operand1 < operand2);
            4'b1100: alu_result <= ~(operand1 | operand2);
        endcase
    end
endmodule

src/ALUControl.v
module ALUControl(
    input wire clk,
    input wire [2:0] funct3,
    output reg [3:0] alu_control
);

    always @(posedge clk) begin
        case (funct3)
            3'b000: alu_control = 4'b0010; // ADDI
            3'b111: alu_control = 4'b0000; // AND
            3'b110: alu_control = 4'b0001; // OR
            3'b010: alu_control = 4'b0111; // SLT
        endcase
    end

endmodule

src/RegisterFile.v
module RegisterFile(
    input wire clk,
    input wire [4:0] read_reg1,
    input wire [4:0] write_reg,
    input wire [31:0] write_data,
    input wire reg_write,   
    output wire [31:0] read_data1
);

    reg [31:0] register[0:31];

    integer i;
    initial begin
        for (i = 0; i < 32; i = i + 1) register[i] = 0;
    end

    always @(posedge clk) begin
    if (reg_write && (write_reg != 5'd0)) begin
        register[write_reg] <= write_data;
    end
    end

    assign read_data1 = (read_reg1 == 5'd0) ? 32'd0 : register[read_reg1];    

endmodule

src/Decoder.v
module Decoder(
    input wire clk,
    input wire [31:0] instruction,
    output wire [6:0] opcode,
    output wire [4:0] rs1,
    output wire [4:0] rd,
    output wire [2:0] funct3,
    output wire [11:0] imm
);
    assign opcode = instruction[6:0];
    assign rd = instruction[11:7];
    assign funct3 = instruction[14:12];
    assign rs1 = instruction[19:15];
    assign imm = instruction[31:20];
    
endmodule

src/IMem.v
module IMem(
    input clk,
    input wire [31:0] addr,
    output wire [31:0] instruction
);
    reg [31:0] memory [0:255];
    assign instruction = memory[addr[9:2]];
    

    initial begin
        $readmemh("program/i_type.txt", memory);
    end
    
    
endmodule

src/PC.v
module PC(
    input clk,
    input reset,
    input wire [31:0] pc_in,
    output reg [31:0] pc_out
);
    always @(posedge clk or posedge reset) begin
        if (reset) begin
            pc_out <= 32'b0;
        end else begin
            pc_out <= pc_in;
        end
    end
    
endmodule

src/CPU.v
module CPU(
    input wire clk,
    input wire reset
);

    wire [31:0] pc_out;

    PC PC(
        .clk(clk), 
        .reset(reset),
        .pc_in(pc_out + 4),
        .pc_out(pc_out)
    );  

    wire [31:0] instruction;

    IMem IMem(
        .clk(clk),
        .addr(pc_out),
        .instruction(instruction)
    );

    wire [6:0] opcode;
    wire [4:0] rs1;
    wire [4:0] rd;
    wire [2:0] funct3;
    wire [11:0] imm;

    Decoder Decoder(
        .clk(clk),
        .instruction(instruction),
        .opcode(opcode),
        .rs1(rs1),
        .rd(rd),
        .funct3(funct3),
        .imm(imm)
    );

    wire [31:0] read_data1;
    wire [31:0] write_data;
    wire reg_write = 1'b1; 
    RegisterFile RegisterFile(
        .clk(clk),
        .read_reg1(rs1),
        .write_reg(rd),
        .write_data(write_data),
        .reg_write(reg_write),
        .read_data1(read_data1)
    );

    wire [3:0] alu_control;
    ALUControl ALUControl(
        .clk(clk),
        .funct3(funct3),
        .alu_control(alu_control)
    );


    wire [31:0] alu_input1 = read_data1;
    wire [31:0] alu_input2 = {{20{imm[11]}}, imm}; // Sign-extend immediate
    wire [31:0] alu_result;
    ALU ALU(
        .clk(clk),
        .operand1(alu_input1),
        .operand2(alu_input2),
        .alu_control(alu_control),
        .alu_result(alu_result)
    );

    assign write_data = alu_result;

endmodule

tb/CPU_testbench.v
module CPU_testbench;
    reg clk = 0;
    reg reset = 0;

    always #1 begin 
        clk = ~clk;
    end

    initial begin
        $dumpfile("CPU_testbench.vcd");
        $dumpvars(0, CPU_testbench);
    end
    
    CPU CPU(
        .clk(clk),
        .reset(reset)
    );

    initial begin
        reset = 1;
        #4
        reset = 0;
        #10
        $finish;
    end

endmodule

CPU_testbench.vcd
$date
	Mon Jan 12 17:14:34 2026
$end
$version
	Icarus Verilog
$end
$timescale
	1s
$end
$scope module CPU_testbench $end
$var reg 1 ! clk $end
$var reg 1 " reset $end
$scope module CPU $end
$var wire 32 # alu_input1 [31:0] $end
$var wire 1 ! clk $end
$var wire 1 $ reg_write $end
$var wire 1 " reset $end
$var wire 32 % write_data [31:0] $end
$var wire 5 & rs1 [4:0] $end
$var wire 32 ' read_data1 [31:0] $end
$var wire 5 ( rd [4:0] $end
$var wire 32 ) pc_out [31:0] $end
$var wire 7 * opcode [6:0] $end
$var wire 32 + instruction [31:0] $end
$var wire 12 , imm [11:0] $end
$var wire 3 - funct3 [2:0] $end
$var wire 32 . alu_result [31:0] $end
$var wire 32 / alu_input2 [31:0] $end
$var wire 4 0 alu_control [3:0] $end
$scope module ALU $end
$var wire 1 ! clk $end
$var wire 32 1 operand1 [31:0] $end
$var wire 32 2 operand2 [31:0] $end
$var wire 4 3 alu_control [3:0] $end
$var reg 32 4 alu_result [31:0] $end
$upscope $end
$scope module ALUControl $end
$var wire 1 ! clk $end
$var wire 3 5 funct3 [2:0] $end
$var reg 4 6 alu_control [3:0] $end
$upscope $end
$scope module Decoder $end
$var wire 1 ! clk $end
$var wire 5 7 rs1 [4:0] $end
$var wire 5 8 rd [4:0] $end
$var wire 7 9 opcode [6:0] $end
$var wire 32 : instruction [31:0] $end
$var wire 12 ; imm [11:0] $end
$var wire 3 < funct3 [2:0] $end
$upscope $end
$scope module IMem $end
$var wire 1 ! clk $end
$var wire 32 = instruction [31:0] $end
$var wire 32 > addr [31:0] $end
$upscope $end
$scope module PC $end
$var wire 1 ! clk $end
$var wire 32 ? pc_in [31:0] $end
$var wire 1 " reset $end
$var reg 32 @ pc_out [31:0] $end
$upscope $end
$scope module RegisterFile $end
$var wire 1 ! clk $end
$var wire 5 A read_reg1 [4:0] $end
$var wire 1 $ reg_write $end
$var wire 32 B write_data [31:0] $end
$var wire 5 C write_reg [4:0] $end
$var wire 32 D read_data1 [31:0] $end
$var integer 32 E i [31:0] $end
$upscope $end
$upscope $end
$upscope $end
$enddefinitions $end
$comment Show the parameter values. $end
$dumpall
$end
#0
$dumpvars
b100000 E
b0 D
b1 C
bx B
b0 A
b0 @
b100 ?
b0 >
b100000000000010010011 =
b0 <
b1 ;
b100000000000010010011 :
b10011 9
b1 8
b0 7
bx 6
b0 5
bx 4
bx 3
b1 2
b0 1
bx 0
b1 /
bx .
b0 -
b1 ,
b100000000000010010011 +
b10011 *
b0 )
b1 (
b0 '
b0 &
bx %
1$
b0 #
1"
0!
$end
#1
b1 %
b1 B
b1 .
b1 4
b10 0
b10 3
b10 6
1!
#2
0!
#3
1!
#4
0!
0"
#5
b10 %
b10 B
b10 .
b10 4
b1 #
b1 1
b1 '
b1 D
b1 &
b1 7
b1 A
b100001000000010010011 +
b100001000000010010011 :
b100001000000010010011 =
b1000 ?
b100 )
b100 >
b100 @
1!
#6
0!
#7
b11 %
b11 B
b11 .
b11 4
b10 #
b10 1
b10 '
b10 D
b1100 ?
b1000 )
b1000 >
b1000 @
1!
#8
0!
#9
b10 %
b10 B
b10 .
b10 4
b11111111111111111111111111111111 /
b11111111111111111111111111111111 2
b111111111111 ,
b111111111111 ;
b11 #
b11 1
b11 '
b11 D
b11111111111100001000000010010011 +
b11111111111100001000000010010011 :
b11111111111100001000000010010011 =
b10000 ?
b1100 )
b1100 >
b1100 @
1!
#10
0!
#11
bx %
bx B
bx .
bx 4
bx /
bx 2
bx ,
bx ;
bx &
bx 7
bx A
bx -
bx 5
bx <
bx (
bx 8
bx C
bx *
bx 9
bx #
bx 1
bx '
bx D
bx +
bx :
bx =
b10100 ?
b10000 )
b10000 >
b10000 @
1!
#12
0!
#13
b11000 ?
b10100 )
b10100 >
b10100 @
1!
